{
    "project_id": "project_91",
    "status": "0",
    "history": [
        {
            "active_devs": -0.4509803921568627,
            "num_commits": -0.9827323106577784,
            "num_files": -0.9477281865701649,
            "num_emails": -0.8842762674504041,
            "c_percentage": 1.0,
            "e_percentage": 0.26984126984126977,
            "inactive_c": -1.0,
            "inactive_e": -0.7931034482758622,
            "c_nodes": -1.0,
            "c_edges": -1.0,
            "c_c_coef": -1.0,
            "c_mean_degree": -1.0,
            "c_long_tail": -1.0,
            "e_nodes": -0.44736842105263164,
            "e_edges": -0.7311178247734139,
            "e_c_coef": -0.08404907262050099,
            "e_mean_degree": -0.1485397784491439,
            "e_long_tail": -0.6774193548387097
        },
        {
            "active_devs": -0.6862745098039216,
            "num_commits": -0.9841779776724761,
            "num_files": -0.9576464280927489,
            "num_emails": -0.9430565760470242,
            "c_percentage": 0.7258883248730965,
            "e_percentage": -0.07096774193548383,
            "inactive_c": 0.1200000000000001,
            "inactive_e": -0.18181818181818177,
            "c_nodes": -0.8709677419354839,
            "c_edges": -0.9913793103448276,
            "c_c_coef": -1.0,
            "c_mean_degree": -0.8663793103448276,
            "c_long_tail": -1.0,
            "e_nodes": -0.7105263157894737,
            "e_edges": -0.8459214501510575,
            "e_c_coef": 0.005922865013774148,
            "e_mean_degree": -0.06852513045866504,
            "e_long_tail": -0.5483870967741935
        },
        {
            "active_devs": -0.607843137254902,
            "num_commits": -0.9998393703317002,
            "num_files": -0.999463878836617,
            "num_emails": -0.9158706833210875,
            "c_percentage": 1.0,
            "e_percentage": 0.10917030567685582,
            "inactive_c": 0.33333333333333326,
            "inactive_e": -0.6,
            "c_nodes": -1.0,
            "c_edges": -1.0,
            "c_c_coef": -1.0,
            "c_mean_degree": -1.0,
            "c_long_tail": -1.0,
            "e_nodes": -0.618421052631579,
            "e_edges": -0.8066465256797584,
            "e_c_coef": -0.44155189436496156,
            "e_mean_degree": -0.11324096260027083,
            "e_long_tail": -0.6129032258064516
        },
        {
            "active_devs": -0.6993464052287581,
            "num_commits": -0.9978314994779536,
            "num_files": -0.9935665460394049,
            "num_emails": -0.9625275532696547,
            "c_percentage": 0.8518518518518521,
            "e_percentage": 0.03921568627450989,
            "inactive_c": 0.5789473684210527,
            "inactive_e": -0.7142857142857144,
            "c_nodes": -1.0,
            "c_edges": -1.0,
            "c_c_coef": -1.0,
            "c_mean_degree": -1.0,
            "c_long_tail": -1.0,
            "e_nodes": -0.7236842105263158,
            "e_edges": -0.9093655589123867,
            "e_c_coef": -0.4111111111111112,
            "e_mean_degree": -0.42598187311178237,
            "e_long_tail": -0.6774193548387097
        },
        {
            "active_devs": -0.673202614379085,
            "num_commits": -0.9975102401413541,
            "num_files": -0.9927623642943305,
            "num_emails": -0.9478324761204996,
            "c_percentage": 0.4193548387096775,
            "e_percentage": -0.11267605633802824,
            "inactive_c": 0.25,
            "inactive_e": -0.5454545454545456,
            "c_nodes": -1.0,
            "c_edges": -1.0,
            "c_c_coef": -1.0,
            "c_mean_degree": -1.0,
            "c_long_tail": -1.0,
            "e_nodes": -0.6842105263157895,
            "e_edges": -0.8489425981873112,
            "e_c_coef": -0.048594461094461194,
            "e_mean_degree": -0.1628902316213493,
            "e_long_tail": -0.5483870967741935
        },
        {
            "active_devs": -0.5947712418300654,
            "num_commits": -0.9989559071560518,
            "num_files": -0.9967832730197025,
            "num_emails": -0.9548126377663483,
            "c_percentage": -0.23076923076923084,
            "e_percentage": -0.10569105691056924,
            "inactive_c": 0.2857142857142858,
            "inactive_e": -0.6666666666666667,
            "c_nodes": -1.0,
            "c_edges": -1.0,
            "c_c_coef": -1.0,
            "c_mean_degree": -1.0,
            "c_long_tail": -1.0,
            "e_nodes": -0.631578947368421,
            "e_edges": -0.8610271903323263,
            "e_c_coef": -0.2059223689475792,
            "e_mean_degree": -0.33987915407854985,
            "e_long_tail": -0.8709677419354839
        },
        {
            "active_devs": -0.6862745098039216,
            "num_commits": -0.9791984579551843,
            "num_files": -0.9798954563731403,
            "num_emails": -0.9507714915503307,
            "c_percentage": 1.0,
            "e_percentage": -0.1343283582089554,
            "inactive_c": -0.7692307692307694,
            "inactive_e": -0.9166666666666667,
            "c_nodes": -1.0,
            "c_edges": -1.0,
            "c_c_coef": -1.0,
            "c_mean_degree": -1.0,
            "c_long_tail": -1.0,
            "e_nodes": -0.6973684210526316,
            "e_edges": -0.8640483383685801,
            "e_c_coef": -0.404843465713031,
            "e_mean_degree": -0.21384473926178893,
            "e_long_tail": -0.4838709677419355
        },
        {
            "active_devs": -0.607843137254902,
            "num_commits": -0.98787246004337,
            "num_files": -0.9782870928829915,
            "num_emails": -0.9448934606906686,
            "c_percentage": 0.3774834437086092,
            "e_percentage": 0.1200000000000001,
            "inactive_c": -0.5172413793103448,
            "inactive_e": -1.0,
            "c_nodes": -0.8709677419354839,
            "c_edges": -0.9913793103448276,
            "c_c_coef": -1.0,
            "c_mean_degree": -0.8663793103448276,
            "c_long_tail": -1.0,
            "e_nodes": -0.6052631578947368,
            "e_edges": -0.8459214501510575,
            "e_c_coef": -0.166984126984127,
            "e_mean_degree": -0.31691842900302114,
            "e_long_tail": -0.7419354838709677
        },
        {
            "active_devs": -0.5294117647058824,
            "num_commits": -0.9748614569110915,
            "num_files": -0.9367377027208149,
            "num_emails": -0.9077883908890522,
            "c_percentage": -0.1693290734824282,
            "e_percentage": 0.26693227091633465,
            "inactive_c": -0.33333333333333337,
            "inactive_e": -0.8571428571428572,
            "c_nodes": -0.6774193548387097,
            "c_edges": -0.9396551724137931,
            "c_c_coef": 0.3999999999999999,
            "c_mean_degree": -0.6258620689655172,
            "c_long_tail": -0.6799999999999999,
            "e_nodes": -0.5921052631578947,
            "e_edges": -0.7915407854984894,
            "e_c_coef": -0.13724447595415323,
            "e_mean_degree": -0.10564272488061588,
            "e_long_tail": -0.7419354838709677
        },
        {
            "active_devs": -0.43790849673202614,
            "num_commits": -0.9881134045458196,
            "num_files": -0.971049457177322,
            "num_emails": -0.8982365907421014,
            "c_percentage": -0.31081081081081097,
            "e_percentage": 0.06859205776173294,
            "inactive_c": -0.5,
            "inactive_e": -0.7142857142857144,
            "c_nodes": -0.6774193548387097,
            "c_edges": -0.9137931034482758,
            "c_c_coef": 1.0,
            "c_mean_degree": -0.4655172413793103,
            "c_long_tail": -1.0,
            "e_nodes": -0.5,
            "e_edges": -0.7492447129909365,
            "e_c_coef": -0.2582942203994836,
            "e_mean_degree": -0.12235649546827787,
            "e_long_tail": -0.6774193548387097
        },
        {
            "active_devs": -0.46405228758169936,
            "num_commits": -0.9919685165850133,
            "num_files": -0.9790912746280659,
            "num_emails": -0.8629684055841293,
            "c_percentage": 0.6399999999999999,
            "e_percentage": 0.260053619302949,
            "inactive_c": -0.23809523809523825,
            "inactive_e": -0.8571428571428572,
            "c_nodes": -0.8709677419354839,
            "c_edges": -0.9913793103448276,
            "c_c_coef": -1.0,
            "c_mean_degree": -0.8663793103448276,
            "c_long_tail": -1.0,
            "e_nodes": -0.5,
            "e_edges": -0.7552870090634441,
            "e_c_coef": -0.23892294839663264,
            "e_mean_degree": -0.14350453172205424,
            "e_long_tail": -0.6774193548387097
        },
        {
            "active_devs": -0.5294117647058824,
            "num_commits": -0.9897197012288169,
            "num_files": -0.9798954563731403,
            "num_emails": -0.914401175606172,
            "c_percentage": 0.734375,
            "e_percentage": 0.0815450643776825,
            "inactive_c": -0.24137931034482762,
            "inactive_e": -0.6551724137931034,
            "c_nodes": -0.8064516129032258,
            "c_edges": -0.9741379310344828,
            "c_c_coef": 1.0,
            "c_mean_degree": -0.7327586206896551,
            "c_long_tail": -1.0,
            "e_nodes": -0.5394736842105263,
            "e_edges": -0.8096676737160121,
            "e_c_coef": -0.33139298796441663,
            "e_mean_degree": -0.2767371601208458,
            "e_long_tail": -0.8064516129032258
        },
        {
            "active_devs": -0.5555555555555556,
            "num_commits": -0.964902417476508,
            "num_files": -0.9134164321136576,
            "num_emails": -0.9103600293901543,
            "c_percentage": -0.2402745995423342,
            "e_percentage": 0.0,
            "inactive_c": -0.2592592592592594,
            "inactive_e": -0.8571428571428572,
            "c_nodes": -0.6129032258064516,
            "c_edges": -0.9310344827586207,
            "c_c_coef": 0.09999999999999987,
            "c_mean_degree": -0.6436781609195402,
            "c_long_tail": -0.6799999999999999,
            "e_nodes": -0.6052631578947368,
            "e_edges": -0.8126888217522659,
            "e_c_coef": -0.1066137566137566,
            "e_mean_degree": -0.16958710976837843,
            "e_long_tail": -0.8064516129032258
        },
        {
            "active_devs": -0.20261437908496727,
            "num_commits": -0.984820496345675,
            "num_files": -0.9622034579815039,
            "num_emails": -0.84313005143277,
            "c_percentage": -0.5555555555555556,
            "e_percentage": 0.025761124121779888,
            "inactive_c": -0.6153846153846154,
            "inactive_e": -1.0,
            "c_nodes": -0.7419354838709677,
            "c_edges": -0.9568965517241379,
            "c_c_coef": 0.6666666666666665,
            "c_mean_degree": -0.665948275862069,
            "c_long_tail": -0.84,
            "e_nodes": -0.26315789473684215,
            "e_edges": -0.5800604229607251,
            "e_c_coef": -0.5015536714010842,
            "e_mean_degree": -0.0026435045317219075,
            "e_long_tail": -0.6129032258064516
        },
        {
            "active_devs": -0.4771241830065359,
            "num_commits": -0.9443418199341418,
            "num_files": -0.8702586784613322,
            "num_emails": -0.9202792064658339,
            "c_percentage": -0.2611832611832612,
            "e_percentage": 0.041474654377880116,
            "inactive_c": -0.33333333333333337,
            "inactive_e": -0.9310344827586208,
            "c_nodes": -0.6774193548387097,
            "c_edges": -0.9137931034482758,
            "c_c_coef": 1.0,
            "c_mean_degree": -0.4655172413793103,
            "c_long_tail": -1.0,
            "e_nodes": -0.5,
            "e_edges": -0.8036253776435045,
            "e_c_coef": -0.525563909774436,
            "e_mean_degree": -0.31268882175226576,
            "e_long_tail": -0.7419354838709677
        },
        {
            "active_devs": -0.46405228758169936,
            "num_commits": -0.9390410408802505,
            "num_files": -0.8185229861948801,
            "num_emails": -0.9059515062454078,
            "c_percentage": 0.8181818181818183,
            "e_percentage": 0.296875,
            "inactive_c": -0.523809523809524,
            "inactive_e": -0.76,
            "c_nodes": -0.8709677419354839,
            "c_edges": -0.9913793103448276,
            "c_c_coef": -1.0,
            "c_mean_degree": -0.8663793103448276,
            "c_long_tail": -1.0,
            "e_nodes": -0.5131578947368421,
            "e_edges": -0.7915407854984894,
            "e_c_coef": -0.2672968535037502,
            "e_mean_degree": -0.2506736343594349,
            "e_long_tail": -0.8709677419354839
        },
        {
            "active_devs": -0.2549019607843137,
            "num_commits": -0.9912456830776645,
            "num_files": -0.9817718804449805,
            "num_emails": -0.855253490080823,
            "c_percentage": 0.3944954128440368,
            "e_percentage": 0.19796954314720816,
            "inactive_c": -0.2857142857142858,
            "inactive_e": -1.0,
            "c_nodes": -0.8064516129032258,
            "c_edges": -0.9827586206896551,
            "c_c_coef": -1.0,
            "c_mean_degree": -0.8218390804597702,
            "c_long_tail": -0.92,
            "e_nodes": -0.26315789473684215,
            "e_edges": -0.6525679758308157,
            "e_c_coef": -0.4039025458668316,
            "e_mean_degree": -0.17484894259818728,
            "e_long_tail": -0.7419354838709677
        },
        {
            "active_devs": -0.3856209150326797,
            "num_commits": -0.9924504055899125,
            "num_files": -0.9801635169548318,
            "num_emails": -0.9335047759000735,
            "c_percentage": 0.9787234042553192,
            "e_percentage": 0.1270718232044199,
            "inactive_c": -0.15789473684210542,
            "inactive_e": -0.5714285714285716,
            "c_nodes": -1.0,
            "c_edges": -1.0,
            "c_c_coef": -1.0,
            "c_mean_degree": -1.0,
            "c_long_tail": -1.0,
            "e_nodes": -0.39473684210526316,
            "e_edges": -0.8006042296072508,
            "e_c_coef": -0.3308610400682014,
            "e_mean_degree": -0.4234861421253119,
            "e_long_tail": -0.935483870967742
        }
    ]
}