{
    "project_id": "project_42",
    "status": "0",
    "history": [
        {
            "active_devs": -0.8545454545454545,
            "num_commits": -0.9944586298690715,
            "num_files": -0.9675982179019846,
            "num_emails": -0.9204831404126824,
            "c_percentage": 0.8431372549019609,
            "e_percentage": 0.06329113924050622,
            "inactive_c": 0.1200000000000001,
            "inactive_e": -0.6,
            "c_nodes": -0.84,
            "c_edges": -0.9826086956521739,
            "c_c_coef": -1.0,
            "c_mean_degree": -0.821917808219178,
            "c_long_tail": -1.0,
            "e_nodes": -0.8571428571428572,
            "e_edges": -0.9225806451612903,
            "e_c_coef": -0.28333333333333344,
            "e_mean_degree": -0.2894736842105263,
            "e_long_tail": -0.7777777777777778
        },
        {
            "active_devs": -0.8363636363636364,
            "num_commits": -0.9961970989297549,
            "num_files": -0.9821790198460916,
            "num_emails": -0.9587317564167086,
            "c_percentage": 0.1428571428571428,
            "e_percentage": -0.41463414634146345,
            "inactive_c": 0.6000000000000001,
            "inactive_e": -0.4545454545454546,
            "c_nodes": -0.84,
            "c_edges": -0.9826086956521739,
            "c_c_coef": -1.0,
            "c_mean_degree": -0.821917808219178,
            "c_long_tail": -1.0,
            "e_nodes": -0.875,
            "e_edges": -0.9225806451612903,
            "e_c_coef": -0.523809523809524,
            "e_mean_degree": -0.18796992481203012,
            "e_long_tail": -0.6296296296296297
        },
        {
            "active_devs": -0.8909090909090909,
            "num_commits": -0.994675938501657,
            "num_files": -0.9821790198460916,
            "num_emails": -0.9718168092601912,
            "c_percentage": 0.18367346938775508,
            "e_percentage": -0.14285714285714302,
            "inactive_c": 0.5555555555555556,
            "inactive_e": -0.2142857142857144,
            "c_nodes": -0.84,
            "c_edges": -0.9826086956521739,
            "c_c_coef": -1.0,
            "c_mean_degree": -0.821917808219178,
            "c_long_tail": -1.0,
            "e_nodes": -0.8928571428571429,
            "e_edges": -0.9419354838709677,
            "e_c_coef": -0.04444444444444462,
            "e_mean_degree": -0.2894736842105263,
            "e_long_tail": -0.7777777777777778
        },
        {
            "active_devs": -0.8727272727272728,
            "num_commits": -0.9994567284185364,
            "num_files": -0.995949777237748,
            "num_emails": -0.9849018621036739,
            "c_percentage": 0.6000000000000001,
            "e_percentage": -0.19999999999999996,
            "inactive_c": 0.7142857142857142,
            "inactive_e": 0.33333333333333326,
            "c_nodes": -1.0,
            "c_edges": -1.0,
            "c_c_coef": -1.0,
            "c_mean_degree": -1.0,
            "c_long_tail": -1.0,
            "e_nodes": -0.9107142857142857,
            "e_edges": -0.9419354838709677,
            "e_c_coef": 0.5333333333333332,
            "e_mean_degree": -0.1473684210526316,
            "e_long_tail": -0.8518518518518519
        },
        {
            "active_devs": -0.8181818181818181,
            "num_commits": -0.9930461237572663,
            "num_files": -0.9619279060348319,
            "num_emails": -0.9194765978862607,
            "c_percentage": 0.8125,
            "e_percentage": -0.07499999999999996,
            "inactive_c": 0.41176470588235303,
            "inactive_e": -0.4814814814814816,
            "c_nodes": -1.0,
            "c_edges": -1.0,
            "c_c_coef": -1.0,
            "c_mean_degree": -1.0,
            "c_long_tail": -1.0,
            "e_nodes": -0.8571428571428572,
            "e_edges": -0.9161290322580645,
            "e_c_coef": -0.17500000000000004,
            "e_mean_degree": -0.23026315789473684,
            "e_long_tail": -0.7037037037037037
        },
        {
            "active_devs": -0.8,
            "num_commits": -0.9938067039713152,
            "num_files": -0.9740785743215877,
            "num_emails": -0.9476597886260695,
            "c_percentage": 0.5087719298245614,
            "e_percentage": -0.1923076923076924,
            "inactive_c": 0.09090909090909083,
            "inactive_e": -0.3076923076923078,
            "c_nodes": -0.84,
            "c_edges": -0.9826086956521739,
            "c_c_coef": -1.0,
            "c_mean_degree": -0.821917808219178,
            "c_long_tail": -1.0,
            "e_nodes": -0.8214285714285714,
            "e_edges": -0.9096774193548387,
            "e_c_coef": -0.6266666666666668,
            "e_mean_degree": -0.33684210526315794,
            "e_long_tail": -0.6296296296296297
        },
        {
            "active_devs": -0.8909090909090909,
            "num_commits": -0.9997826913674146,
            "num_files": -0.9983799108950993,
            "num_emails": -0.9778560644187217,
            "c_percentage": 0.0,
            "e_percentage": 0.0,
            "inactive_c": -1.0,
            "inactive_e": 0.40740740740740744,
            "c_nodes": -1.0,
            "c_edges": -1.0,
            "c_c_coef": -1.0,
            "c_mean_degree": -1.0,
            "c_long_tail": -1.0,
            "e_nodes": -0.9107142857142857,
            "e_edges": -0.9483870967741935,
            "e_c_coef": -0.1333333333333332,
            "e_mean_degree": -0.2421052631578947,
            "e_long_tail": -0.7777777777777778
        },
        {
            "active_devs": -0.8,
            "num_commits": -0.9991307654696583,
            "num_files": -0.995949777237748,
            "num_emails": -0.9235027679919476,
            "c_percentage": 0.5,
            "e_percentage": 0.07894736842105265,
            "inactive_c": -0.33333333333333337,
            "inactive_e": -0.5555555555555556,
            "c_nodes": -0.84,
            "c_edges": -0.9826086956521739,
            "c_c_coef": -1.0,
            "c_mean_degree": -0.821917808219178,
            "c_long_tail": -1.0,
            "e_nodes": -0.8214285714285714,
            "e_edges": -0.9096774193548387,
            "e_c_coef": -0.4476190476190476,
            "e_mean_degree": -0.33684210526315794,
            "e_long_tail": -0.9259259259259259
        },
        {
            "active_devs": -0.8909090909090909,
            "num_commits": -0.9996740370511219,
            "num_files": -0.9975698663426489,
            "num_emails": -0.9859084046300957,
            "c_percentage": 1.0,
            "e_percentage": 0.1428571428571428,
            "inactive_c": -1.0,
            "inactive_e": 0.46666666666666656,
            "c_nodes": -1.0,
            "c_edges": -1.0,
            "c_c_coef": -1.0,
            "c_mean_degree": -1.0,
            "c_long_tail": -1.0,
            "e_nodes": -0.9107142857142857,
            "e_edges": -0.967741935483871,
            "e_c_coef": -1.0,
            "e_mean_degree": -0.5263157894736843,
            "e_long_tail": -0.9259259259259259
        },
        {
            "active_devs": -0.8909090909090909,
            "num_commits": -1.0,
            "num_files": -1.0,
            "num_emails": -0.9899345747357826,
            "c_percentage": -1.0,
            "e_percentage": -0.6,
            "inactive_c": 1.0,
            "inactive_e": 0.368421052631579,
            "c_nodes": -1.0,
            "c_edges": -1.0,
            "c_c_coef": -1.0,
            "c_mean_degree": -1.0,
            "c_long_tail": -1.0,
            "e_nodes": -0.8928571428571429,
            "e_edges": -0.9612903225806452,
            "e_c_coef": -0.2777777777777778,
            "e_mean_degree": -0.5263157894736843,
            "e_long_tail": -0.7037037037037037
        },
        {
            "active_devs": -0.9454545454545454,
            "num_commits": -1.0,
            "num_files": -1.0,
            "num_emails": -0.9899345747357826,
            "c_percentage": -1.0,
            "e_percentage": 0.0,
            "inactive_c": 1.0,
            "inactive_e": -0.25,
            "c_nodes": -1.0,
            "c_edges": -1.0,
            "c_c_coef": -1.0,
            "c_mean_degree": -1.0,
            "c_long_tail": -1.0,
            "e_nodes": -0.9464285714285714,
            "e_edges": -0.9806451612903225,
            "e_c_coef": -1.0,
            "e_mean_degree": -0.5263157894736843,
            "e_long_tail": -0.8518518518518519
        },
        {
            "active_devs": -0.8545454545454545,
            "num_commits": -0.9986961482044874,
            "num_files": -0.9910895099230458,
            "num_emails": -0.9869149471565174,
            "c_percentage": 0.6666666666666667,
            "e_percentage": -0.3846153846153846,
            "inactive_c": 0.8823529411764703,
            "inactive_e": 0.52,
            "c_nodes": -1.0,
            "c_edges": -1.0,
            "c_c_coef": -1.0,
            "c_mean_degree": -1.0,
            "c_long_tail": -1.0,
            "e_nodes": -0.875,
            "e_edges": -0.9548387096774194,
            "e_c_coef": -1.0,
            "e_mean_degree": -0.5263157894736843,
            "e_long_tail": -0.9259259259259259
        },
        {
            "active_devs": -0.9272727272727272,
            "num_commits": -0.9997826913674146,
            "num_files": -0.9983799108950993,
            "num_emails": -0.9969803724207348,
            "c_percentage": 0.0,
            "e_percentage": 0.33333333333333326,
            "inactive_c": 0.0,
            "inactive_e": 0.0,
            "c_nodes": -1.0,
            "c_edges": -1.0,
            "c_c_coef": -1.0,
            "c_mean_degree": -1.0,
            "c_long_tail": -1.0,
            "e_nodes": -0.9285714285714286,
            "e_edges": -0.9870967741935484,
            "e_c_coef": -1.0,
            "e_mean_degree": -0.7631578947368421,
            "e_long_tail": -1.0
        },
        {
            "active_devs": -1.0,
            "num_commits": -1.0,
            "num_files": -1.0,
            "num_emails": -1.0,
            "c_percentage": -1.0,
            "e_percentage": -1.0,
            "inactive_c": 1.0,
            "inactive_e": 1.0,
            "c_nodes": -1.0,
            "c_edges": -1.0,
            "c_c_coef": -1.0,
            "c_mean_degree": -1.0,
            "c_long_tail": -1.0,
            "e_nodes": -1.0,
            "e_edges": -1.0,
            "e_c_coef": -1.0,
            "e_mean_degree": -1.0,
            "e_long_tail": -1.0
        },
        {
            "active_devs": -0.8363636363636364,
            "num_commits": -1.0,
            "num_files": -1.0,
            "num_emails": -0.9516859587317564,
            "c_percentage": -1.0,
            "e_percentage": -0.08333333333333337,
            "inactive_c": 1.0,
            "inactive_e": -0.15789473684210542,
            "c_nodes": -1.0,
            "c_edges": -1.0,
            "c_c_coef": -1.0,
            "c_mean_degree": -1.0,
            "c_long_tail": -1.0,
            "e_nodes": -0.8392857142857143,
            "e_edges": -0.9290322580645162,
            "e_c_coef": -0.5476190476190478,
            "e_mean_degree": -0.42105263157894735,
            "e_long_tail": -0.8518518518518519
        },
        {
            "active_devs": -0.8727272727272728,
            "num_commits": -0.9881566795240941,
            "num_files": -0.9238558120696638,
            "num_emails": -0.9073980875691998,
            "c_percentage": 0.06422018348623859,
            "e_percentage": -0.021739130434782594,
            "inactive_c": 0.0,
            "inactive_e": -0.33333333333333337,
            "c_nodes": -0.84,
            "c_edges": -0.9826086956521739,
            "c_c_coef": -1.0,
            "c_mean_degree": -0.821917808219178,
            "c_long_tail": -1.0,
            "e_nodes": -0.875,
            "e_edges": -0.896774193548387,
            "e_c_coef": 0.6476190476190478,
            "e_mean_degree": 0.08270676691729317,
            "e_long_tail": -0.7037037037037037
        },
        {
            "active_devs": -0.8363636363636364,
            "num_commits": -0.9979355679904384,
            "num_files": -0.989469420818145,
            "num_emails": -0.9406139909411173,
            "c_percentage": 1.0,
            "e_percentage": 0.016949152542372836,
            "inactive_c": -0.19999999999999996,
            "inactive_e": -0.26315789473684215,
            "c_nodes": -1.0,
            "c_edges": -1.0,
            "c_c_coef": -1.0,
            "c_mean_degree": -1.0,
            "c_long_tail": -1.0,
            "e_nodes": -0.8035714285714286,
            "e_edges": -0.8838709677419355,
            "e_c_coef": -0.3171717171717172,
            "e_mean_degree": -0.22488038277511957,
            "e_long_tail": -0.7777777777777778
        },
        {
            "active_devs": -0.6000000000000001,
            "num_commits": -0.8707013636116695,
            "num_files": -0.4491697043337384,
            "num_emails": -0.7564167086059386,
            "c_percentage": 0.9478991596638655,
            "e_percentage": 0.3471074380165289,
            "inactive_c": -0.5555555555555556,
            "inactive_e": -0.6923076923076924,
            "c_nodes": -0.84,
            "c_edges": -0.9826086956521739,
            "c_c_coef": -1.0,
            "c_mean_degree": -0.821917808219178,
            "c_long_tail": -1.0,
            "e_nodes": -0.6071428571428572,
            "e_edges": -0.7612903225806451,
            "e_c_coef": -0.27165775401069525,
            "e_mean_degree": -0.2033492822966506,
            "e_long_tail": -0.7037037037037037
        },
        {
            "active_devs": -0.7090909090909091,
            "num_commits": -0.8559243765958603,
            "num_files": -0.3454840016200891,
            "num_emails": -0.8117765475591343,
            "c_percentage": 0.7104072398190044,
            "e_percentage": 0.7112299465240641,
            "inactive_c": -0.3846153846153846,
            "inactive_e": -0.5833333333333335,
            "c_nodes": -0.84,
            "c_edges": -0.9826086956521739,
            "c_c_coef": -1.0,
            "c_mean_degree": -0.821917808219178,
            "c_long_tail": -1.0,
            "e_nodes": -0.7142857142857143,
            "e_edges": -0.8516129032258064,
            "e_c_coef": -0.78125,
            "e_mean_degree": -0.31907894736842113,
            "e_long_tail": -0.7777777777777778
        },
        {
            "active_devs": -0.8545454545454545,
            "num_commits": -0.9244852501765632,
            "num_files": -0.8509518023491291,
            "num_emails": -0.9788626069451434,
            "c_percentage": 0.8676258992805752,
            "e_percentage": -0.33333333333333337,
            "inactive_c": 0.10344827586206895,
            "inactive_e": -0.6,
            "c_nodes": -1.0,
            "c_edges": -1.0,
            "c_c_coef": -1.0,
            "c_mean_degree": -1.0,
            "c_long_tail": -1.0,
            "e_nodes": -0.875,
            "e_edges": -0.9483870967741935,
            "e_c_coef": -0.4,
            "e_mean_degree": -0.4586466165413534,
            "e_long_tail": -0.8518518518518519
        },
        {
            "active_devs": -0.7636363636363637,
            "num_commits": -0.9511055576682784,
            "num_files": -0.6784123126771973,
            "num_emails": -0.9386009058882738,
            "c_percentage": 0.1511111111111112,
            "e_percentage": 0.34426229508196715,
            "inactive_c": 0.25,
            "inactive_e": -0.18181818181818177,
            "c_nodes": -1.0,
            "c_edges": -1.0,
            "c_c_coef": -1.0,
            "c_mean_degree": -1.0,
            "c_long_tail": -1.0,
            "e_nodes": -0.7678571428571429,
            "e_edges": -0.8838709677419355,
            "e_c_coef": -0.5787545787545788,
            "e_mean_degree": -0.3441295546558705,
            "e_long_tail": -0.7777777777777778
        },
        {
            "active_devs": -0.8727272727272728,
            "num_commits": -0.9957624816645841,
            "num_files": -0.9724584852166869,
            "num_emails": -0.9466532460996477,
            "c_percentage": 1.0,
            "e_percentage": 0.28301886792452824,
            "inactive_c": 0.5238095238095237,
            "inactive_e": -0.0370370370370372,
            "c_nodes": -1.0,
            "c_edges": -1.0,
            "c_c_coef": -1.0,
            "c_mean_degree": -1.0,
            "c_long_tail": -1.0,
            "e_nodes": -0.8392857142857143,
            "e_edges": -0.9290322580645162,
            "e_c_coef": -0.5343915343915344,
            "e_mean_degree": -0.42105263157894735,
            "e_long_tail": -0.9259259259259259
        },
        {
            "active_devs": -0.8363636363636364,
            "num_commits": -0.9993480741022437,
            "num_files": -0.9951397326852977,
            "num_emails": -0.9305485656768998,
            "c_percentage": 0.0,
            "e_percentage": 0.07246376811594213,
            "inactive_c": 0.7777777777777777,
            "inactive_e": -0.5,
            "c_nodes": -1.0,
            "c_edges": -1.0,
            "c_c_coef": -1.0,
            "c_mean_degree": -1.0,
            "c_long_tail": -1.0,
            "e_nodes": -0.8392857142857143,
            "e_edges": -0.9225806451612903,
            "e_c_coef": -0.09523809523809545,
            "e_mean_degree": -0.368421052631579,
            "e_long_tail": -0.8518518518518519
        },
        {
            "active_devs": -0.9454545454545454,
            "num_commits": -1.0,
            "num_files": -1.0,
            "num_emails": -0.9939607448414696,
            "c_percentage": -1.0,
            "e_percentage": 0.0,
            "inactive_c": 1.0,
            "inactive_e": 0.875,
            "c_nodes": -1.0,
            "c_edges": -1.0,
            "c_c_coef": -1.0,
            "c_mean_degree": -1.0,
            "c_long_tail": -1.0,
            "e_nodes": -0.9285714285714286,
            "e_edges": -0.9741935483870968,
            "e_c_coef": 0.16666666666666652,
            "e_mean_degree": -0.5263157894736843,
            "e_long_tail": -0.7777777777777778
        },
        {
            "active_devs": -0.9454545454545454,
            "num_commits": -1.0,
            "num_files": -1.0,
            "num_emails": -0.9939607448414696,
            "c_percentage": -1.0,
            "e_percentage": -0.33333333333333337,
            "inactive_c": 1.0,
            "inactive_e": 0.6842105263157894,
            "c_nodes": -1.0,
            "c_edges": -1.0,
            "c_c_coef": -1.0,
            "c_mean_degree": -1.0,
            "c_long_tail": -1.0,
            "e_nodes": -0.9464285714285714,
            "e_edges": -0.9870967741935484,
            "e_c_coef": -1.0,
            "e_mean_degree": -0.6842105263157895,
            "e_long_tail": -0.9259259259259259
        },
        {
            "active_devs": -1.0,
            "num_commits": -1.0,
            "num_files": -1.0,
            "num_emails": -1.0,
            "c_percentage": -1.0,
            "e_percentage": -1.0,
            "inactive_c": 1.0,
            "inactive_e": 1.0,
            "c_nodes": -1.0,
            "c_edges": -1.0,
            "c_c_coef": -1.0,
            "c_mean_degree": -1.0,
            "c_long_tail": -1.0,
            "e_nodes": -1.0,
            "e_edges": -1.0,
            "e_c_coef": -1.0,
            "e_mean_degree": -1.0,
            "e_long_tail": -1.0
        },
        {
            "active_devs": -1.0,
            "num_commits": -1.0,
            "num_files": -1.0,
            "num_emails": -1.0,
            "c_percentage": -1.0,
            "e_percentage": -1.0,
            "inactive_c": 1.0,
            "inactive_e": 1.0,
            "c_nodes": -1.0,
            "c_edges": -1.0,
            "c_c_coef": -1.0,
            "c_mean_degree": -1.0,
            "c_long_tail": -1.0,
            "e_nodes": -1.0,
            "e_edges": -1.0,
            "e_c_coef": -1.0,
            "e_mean_degree": -1.0,
            "e_long_tail": -1.0
        }
    ]
}