{
    "project_id": "project_206",
    "status": "1",
    "history": [
        {
            "active_devs": -0.8736059479553904,
            "num_commits": -1.0,
            "num_files": -1.0,
            "num_emails": -0.9507042253521126,
            "c_percentage": -1.0,
            "e_percentage": -0.2857142857142858,
            "inactive_c": 1.0,
            "inactive_e": -0.8095238095238095,
            "c_nodes": -1.0,
            "c_edges": -1.0,
            "c_c_coef": -1.0,
            "c_mean_degree": -1.0,
            "c_long_tail": -1.0,
            "e_nodes": -0.8661710037174721,
            "e_edges": -0.9467275494672756,
            "e_c_coef": -0.3410052910052912,
            "e_mean_degree": -0.22609176340519632,
            "e_long_tail": -0.5757575757575757
        },
        {
            "active_devs": -0.8661710037174721,
            "num_commits": -1.0,
            "num_files": -1.0,
            "num_emails": -0.9502012072434608,
            "c_percentage": -1.0,
            "e_percentage": -0.13131313131313138,
            "inactive_c": 1.0,
            "inactive_e": -0.7037037037037037,
            "c_nodes": -1.0,
            "c_edges": -1.0,
            "c_c_coef": -1.0,
            "c_mean_degree": -1.0,
            "c_long_tail": -1.0,
            "e_nodes": -0.8661710037174721,
            "e_edges": -0.9512937595129376,
            "e_c_coef": -0.2707231040564374,
            "e_mean_degree": -0.2924267551133223,
            "e_long_tail": -0.6363636363636364
        },
        {
            "active_devs": -0.9033457249070632,
            "num_commits": -1.0,
            "num_files": -1.0,
            "num_emails": -0.9768611670020121,
            "c_percentage": -1.0,
            "e_percentage": -0.0869565217391306,
            "inactive_c": 1.0,
            "inactive_e": -0.125,
            "c_nodes": -1.0,
            "c_edges": -1.0,
            "c_c_coef": -1.0,
            "c_mean_degree": -1.0,
            "c_long_tail": -1.0,
            "e_nodes": -0.9033457249070632,
            "e_edges": -0.974124809741248,
            "e_c_coef": -0.4717948717948718,
            "e_mean_degree": -0.47952544967470345,
            "e_long_tail": -0.696969696969697
        }
    ]
}