{
    "project_id": "project_152",
    "status": "0",
    "history": [
        {
            "active_devs": -0.9553903345724907,
            "num_commits": -1.0,
            "num_files": -1.0,
            "num_emails": -0.9914486921529175,
            "c_percentage": -1.0,
            "e_percentage": -0.2941176470588236,
            "inactive_c": 1.0,
            "inactive_e": 0.2857142857142858,
            "c_nodes": -1.0,
            "c_edges": -1.0,
            "c_c_coef": -1.0,
            "c_mean_degree": -1.0,
            "c_long_tail": -1.0,
            "e_nodes": -0.9479553903345725,
            "e_edges": -0.9893455098934552,
            "e_c_coef": -1.0,
            "e_mean_degree": -0.6019900497512438,
            "e_long_tail": -0.8787878787878788
        },
        {
            "active_devs": -0.9330855018587361,
            "num_commits": -0.9946960636472363,
            "num_files": -0.9898408398239079,
            "num_emails": -0.9381287726358148,
            "c_percentage": 1.0,
            "e_percentage": 0.15447154471544722,
            "inactive_c": 0.8666666666666665,
            "inactive_e": -0.2142857142857144,
            "c_nodes": -1.0,
            "c_edges": -1.0,
            "c_c_coef": -1.0,
            "c_mean_degree": -1.0,
            "c_long_tail": -1.0,
            "e_nodes": -0.9107806691449815,
            "e_edges": -0.9710806697108068,
            "e_c_coef": -0.03968253968253965,
            "e_mean_degree": -0.36981757877280275,
            "e_long_tail": -0.696969696969697
        },
        {
            "active_devs": -0.8364312267657993,
            "num_commits": -0.9019291768498778,
            "num_files": -0.9095834744327802,
            "num_emails": -0.9285714285714286,
            "c_percentage": -0.4294803817603394,
            "e_percentage": -0.3380281690140846,
            "inactive_c": -0.7272727272727274,
            "inactive_e": -0.7037037037037037,
            "c_nodes": -0.43999999999999995,
            "c_edges": -0.8992248062015504,
            "c_c_coef": 0.8476190476190479,
            "c_mean_degree": -0.6400885935769658,
            "c_long_tail": -0.5652173913043479,
            "e_nodes": -0.895910780669145,
            "e_edges": -0.9360730593607306,
            "e_c_coef": 0.18015873015873018,
            "e_mean_degree": 0.19402985074626855,
            "e_long_tail": -0.3939393939393939
        }
    ]
}