{
    "project_id": "112",
    "status": "1",
    "history": [
        {
            "active_devs": 32.0,
            "num_commits": 0.0,
            "num_files": 0.0,
            "num_emails": 169.0,
            "c_percentage": 0.0,
            "e_percentage": 0.5029585798816568,
            "inactive_c": 1.0,
            "inactive_e": 0.1111111111111111,
            "c_nodes": 0.0,
            "c_edges": 0.0,
            "c_c_coef": 0.0,
            "c_mean_degree": 0.0,
            "c_long_tail": 0.0,
            "e_nodes": 37.0,
            "e_edges": 71.0,
            "e_c_coef": 0.2142064524417465,
            "e_mean_degree": 3.8378378378378377,
            "e_long_tail": 6.0
        },
        {
            "active_devs": 58.0,
            "num_commits": 0.0,
            "num_files": 0.0,
            "num_emails": 410.0,
            "c_percentage": 0.0,
            "e_percentage": 0.5292682926829269,
            "inactive_c": 1.0,
            "inactive_e": 0.1785714285714285,
            "c_nodes": 0.0,
            "c_edges": 0.0,
            "c_c_coef": 0.0,
            "c_mean_degree": 0.0,
            "c_long_tail": 0.0,
            "e_nodes": 58.0,
            "e_edges": 141.0,
            "e_c_coef": 0.3183474121100895,
            "e_mean_degree": 4.862068965517241,
            "e_long_tail": 8.0
        },
        {
            "active_devs": 33.0,
            "num_commits": 145.0,
            "num_files": 91.0,
            "num_emails": 189.0,
            "c_percentage": 1.0,
            "e_percentage": 0.5925925925925926,
            "inactive_c": 0.2222222222222222,
            "inactive_e": 0.2758620689655172,
            "c_nodes": 0.0,
            "c_edges": 0.0,
            "c_c_coef": 0.0,
            "c_mean_degree": 0.0,
            "c_long_tail": 0.0,
            "e_nodes": 32.0,
            "e_edges": 55.0,
            "e_c_coef": 0.2128787878787879,
            "e_mean_degree": 3.4375,
            "e_long_tail": 4.0
        },
        {
            "active_devs": 20.0,
            "num_commits": 260.0,
            "num_files": 103.0,
            "num_emails": 83.0,
            "c_percentage": 0.5769230769230769,
            "e_percentage": 0.5301204819277109,
            "inactive_c": 0.4285714285714285,
            "inactive_e": 0.2592592592592592,
            "c_nodes": 2.0,
            "c_edges": 1.0,
            "c_c_coef": 0.0,
            "c_mean_degree": 1.0,
            "c_long_tail": 0.0,
            "e_nodes": 19.0,
            "e_edges": 29.0,
            "e_c_coef": 0.2881977671451355,
            "e_mean_degree": 3.0526315789473686,
            "e_long_tail": 3.0
        },
        {
            "active_devs": 3.0,
            "num_commits": 0.0,
            "num_files": 0.0,
            "num_emails": 5.0,
            "c_percentage": 0.0,
            "e_percentage": 0.6,
            "inactive_c": 1.0,
            "inactive_e": 0.25,
            "c_nodes": 0.0,
            "c_edges": 0.0,
            "c_c_coef": 0.0,
            "c_mean_degree": 0.0,
            "c_long_tail": 0.0,
            "e_nodes": 4.0,
            "e_edges": 3.0,
            "e_c_coef": 0.0,
            "e_mean_degree": 1.5,
            "e_long_tail": 1.0
        },
        {
            "active_devs": 19.0,
            "num_commits": 169.0,
            "num_files": 153.0,
            "num_emails": 107.0,
            "c_percentage": 0.7928994082840237,
            "e_percentage": 0.5046728971962616,
            "inactive_c": 0.6153846153846154,
            "inactive_e": 0.2307692307692307,
            "c_nodes": 3.0,
            "c_edges": 2.0,
            "c_c_coef": 0.0,
            "c_mean_degree": 1.3333333333333333,
            "c_long_tail": 1.0,
            "e_nodes": 15.0,
            "e_edges": 25.0,
            "e_c_coef": 0.3785185185185185,
            "e_mean_degree": 3.333333333333333,
            "e_long_tail": 5.0
        },
        {
            "active_devs": 22.0,
            "num_commits": 148.0,
            "num_files": 122.0,
            "num_emails": 82.0,
            "c_percentage": 0.4662162162162162,
            "e_percentage": 0.3780487804878049,
            "inactive_c": 0.6666666666666666,
            "inactive_e": 0.2,
            "c_nodes": 4.0,
            "c_edges": 5.0,
            "c_c_coef": 0.8333333333333333,
            "c_mean_degree": 2.5,
            "c_long_tail": 2.0,
            "e_nodes": 19.0,
            "e_edges": 31.0,
            "e_c_coef": 0.3908939014202172,
            "e_mean_degree": 3.263157894736842,
            "e_long_tail": 5.0
        },
        {
            "active_devs": 25.0,
            "num_commits": 29.0,
            "num_files": 27.0,
            "num_emails": 159.0,
            "c_percentage": 1.0,
            "e_percentage": 0.4842767295597484,
            "inactive_c": 0.0,
            "inactive_e": 0.0689655172413793,
            "c_nodes": 0.0,
            "c_edges": 0.0,
            "c_c_coef": 0.0,
            "c_mean_degree": 0.0,
            "c_long_tail": 0.0,
            "e_nodes": 26.0,
            "e_edges": 51.0,
            "e_c_coef": 0.4558889828120597,
            "e_mean_degree": 3.923076923076923,
            "e_long_tail": 7.0
        },
        {
            "active_devs": 15.0,
            "num_commits": 440.0,
            "num_files": 271.0,
            "num_emails": 111.0,
            "c_percentage": 0.6659090909090909,
            "e_percentage": 0.4234234234234234,
            "inactive_c": 0.4117647058823529,
            "inactive_e": 0.0689655172413793,
            "c_nodes": 3.0,
            "c_edges": 3.0,
            "c_c_coef": 1.0,
            "c_mean_degree": 2.0,
            "c_long_tail": 0.0,
            "e_nodes": 13.0,
            "e_edges": 32.0,
            "e_c_coef": 0.5081807081807082,
            "e_mean_degree": 4.923076923076923,
            "e_long_tail": 7.0
        },
        {
            "active_devs": 14.0,
            "num_commits": 634.0,
            "num_files": 315.0,
            "num_emails": 106.0,
            "c_percentage": 0.5173501577287066,
            "e_percentage": 0.5,
            "inactive_c": 0.7391304347826086,
            "inactive_e": 0.2222222222222222,
            "c_nodes": 3.0,
            "c_edges": 2.0,
            "c_c_coef": 0.0,
            "c_mean_degree": 1.3333333333333333,
            "c_long_tail": 1.0,
            "e_nodes": 12.0,
            "e_edges": 22.0,
            "e_c_coef": 0.4956349206349206,
            "e_mean_degree": 3.6666666666666665,
            "e_long_tail": 7.0
        },
        {
            "active_devs": 19.0,
            "num_commits": 255.0,
            "num_files": 129.0,
            "num_emails": 78.0,
            "c_percentage": 0.6588235294117647,
            "e_percentage": 0.358974358974359,
            "inactive_c": 0.5238095238095238,
            "inactive_e": 0.4,
            "c_nodes": 2.0,
            "c_edges": 1.0,
            "c_c_coef": 0.0,
            "c_mean_degree": 1.0,
            "c_long_tail": 0.0,
            "e_nodes": 17.0,
            "e_edges": 29.0,
            "e_c_coef": 0.3148459383753501,
            "e_mean_degree": 3.411764705882353,
            "e_long_tail": 7.0
        },
        {
            "active_devs": 24.0,
            "num_commits": 1638.0,
            "num_files": 537.0,
            "num_emails": 180.0,
            "c_percentage": 0.5525030525030525,
            "e_percentage": 0.4166666666666667,
            "inactive_c": 0.28,
            "inactive_e": 0.0689655172413793,
            "c_nodes": 4.0,
            "c_edges": 5.0,
            "c_c_coef": 0.8333333333333333,
            "c_mean_degree": 2.5,
            "c_long_tail": 2.0,
            "e_nodes": 20.0,
            "e_edges": 40.0,
            "e_c_coef": 0.4079004329004329,
            "e_mean_degree": 4.0,
            "e_long_tail": 7.0
        },
        {
            "active_devs": 32.0,
            "num_commits": 1682.0,
            "num_files": 740.0,
            "num_emails": 179.0,
            "c_percentage": 0.6872770511296076,
            "e_percentage": 0.5251396648044693,
            "inactive_c": 0.3571428571428571,
            "inactive_e": 0.0344827586206896,
            "c_nodes": 4.0,
            "c_edges": 5.0,
            "c_c_coef": 0.8333333333333333,
            "c_mean_degree": 2.5,
            "c_long_tail": 2.0,
            "e_nodes": 29.0,
            "e_edges": 55.0,
            "e_c_coef": 0.4345009313525055,
            "e_mean_degree": 3.793103448275862,
            "e_long_tail": 2.0
        },
        {
            "active_devs": 27.0,
            "num_commits": 894.0,
            "num_files": 817.0,
            "num_emails": 236.0,
            "c_percentage": 0.9228187919463088,
            "e_percentage": 0.4703389830508475,
            "inactive_c": 0.6,
            "inactive_e": 0.0,
            "c_nodes": 3.0,
            "c_edges": 3.0,
            "c_c_coef": 1.0,
            "c_mean_degree": 2.0,
            "c_long_tail": 0.0,
            "e_nodes": 24.0,
            "e_edges": 71.0,
            "e_c_coef": 0.5882071632071632,
            "e_mean_degree": 5.916666666666667,
            "e_long_tail": 9.0
        },
        {
            "active_devs": 26.0,
            "num_commits": 215.0,
            "num_files": 121.0,
            "num_emails": 151.0,
            "c_percentage": 0.5255813953488372,
            "e_percentage": 0.5165562913907285,
            "inactive_c": 0.7647058823529411,
            "inactive_e": 0.0357142857142857,
            "c_nodes": 4.0,
            "c_edges": 3.0,
            "c_c_coef": 0.0,
            "c_mean_degree": 1.5,
            "c_long_tail": 2.0,
            "e_nodes": 22.0,
            "e_edges": 46.0,
            "e_c_coef": 0.4535353535353535,
            "e_mean_degree": 4.181818181818182,
            "e_long_tail": 10.0
        },
        {
            "active_devs": 26.0,
            "num_commits": 139.0,
            "num_files": 91.0,
            "num_emails": 134.0,
            "c_percentage": 1.0,
            "e_percentage": 0.4552238805970149,
            "inactive_c": 0.6956521739130435,
            "inactive_e": 0.0689655172413793,
            "c_nodes": 0.0,
            "c_edges": 0.0,
            "c_c_coef": 0.0,
            "c_mean_degree": 0.0,
            "c_long_tail": 0.0,
            "e_nodes": 26.0,
            "e_edges": 51.0,
            "e_c_coef": 0.2191112306496922,
            "e_mean_degree": 3.923076923076923,
            "e_long_tail": 8.0
        },
        {
            "active_devs": 27.0,
            "num_commits": 1.0,
            "num_files": 1.0,
            "num_emails": 168.0,
            "c_percentage": 1.0,
            "e_percentage": 0.3630952380952381,
            "inactive_c": 0.0,
            "inactive_e": 0.0714285714285714,
            "c_nodes": 0.0,
            "c_edges": 0.0,
            "c_c_coef": 0.0,
            "c_mean_degree": 0.0,
            "c_long_tail": 0.0,
            "e_nodes": 27.0,
            "e_edges": 59.0,
            "e_c_coef": 0.2862610640388419,
            "e_mean_degree": 4.37037037037037,
            "e_long_tail": 11.0
        },
        {
            "active_devs": 15.0,
            "num_commits": 315.0,
            "num_files": 267.0,
            "num_emails": 61.0,
            "c_percentage": 0.6952380952380952,
            "e_percentage": 0.4754098360655737,
            "inactive_c": 0.9375,
            "inactive_e": 0.2692307692307692,
            "c_nodes": 2.0,
            "c_edges": 1.0,
            "c_c_coef": 0.0,
            "c_mean_degree": 1.0,
            "c_long_tail": 0.0,
            "e_nodes": 13.0,
            "e_edges": 22.0,
            "e_c_coef": 0.2897435897435897,
            "e_mean_degree": 3.3846153846153846,
            "e_long_tail": 7.0
        },
        {
            "active_devs": 23.0,
            "num_commits": 559.0,
            "num_files": 425.0,
            "num_emails": 128.0,
            "c_percentage": 0.6726296958855098,
            "e_percentage": 0.2734375,
            "inactive_c": 0.9375,
            "inactive_e": 0.0357142857142857,
            "c_nodes": 3.0,
            "c_edges": 2.0,
            "c_c_coef": 0.0,
            "c_mean_degree": 1.3333333333333333,
            "c_long_tail": 1.0,
            "e_nodes": 20.0,
            "e_edges": 41.0,
            "e_c_coef": 0.3661111111111111,
            "e_mean_degree": 4.1,
            "e_long_tail": 10.0
        },
        {
            "active_devs": 31.0,
            "num_commits": 390.0,
            "num_files": 263.0,
            "num_emails": 197.0,
            "c_percentage": 0.7461538461538462,
            "e_percentage": 0.3401015228426396,
            "inactive_c": 0.3888888888888889,
            "inactive_e": 0.0344827586206896,
            "c_nodes": 3.0,
            "c_edges": 3.0,
            "c_c_coef": 1.0,
            "c_mean_degree": 2.0,
            "c_long_tail": 0.0,
            "e_nodes": 30.0,
            "e_edges": 59.0,
            "e_c_coef": 0.218994708994709,
            "e_mean_degree": 3.933333333333333,
            "e_long_tail": 12.0
        },
        {
            "active_devs": 29.0,
            "num_commits": 934.0,
            "num_files": 531.0,
            "num_emails": 217.0,
            "c_percentage": 0.6466809421841542,
            "e_percentage": 0.3225806451612903,
            "inactive_c": 0.75,
            "inactive_e": 0.1034482758620689,
            "c_nodes": 2.0,
            "c_edges": 1.0,
            "c_c_coef": 0.0,
            "c_mean_degree": 1.0,
            "c_long_tail": 0.0,
            "e_nodes": 28.0,
            "e_edges": 49.0,
            "e_c_coef": 0.1202380952380952,
            "e_mean_degree": 3.5,
            "e_long_tail": 17.0
        },
        {
            "active_devs": 36.0,
            "num_commits": 2040.0,
            "num_files": 801.0,
            "num_emails": 146.0,
            "c_percentage": 0.5357843137254902,
            "e_percentage": 0.4931506849315068,
            "inactive_c": 0.1428571428571428,
            "inactive_e": 0.1379310344827586,
            "c_nodes": 8.0,
            "c_edges": 20.0,
            "c_c_coef": 0.8547619047619048,
            "c_mean_degree": 5.0,
            "c_long_tail": 7.0,
            "e_nodes": 29.0,
            "e_edges": 44.0,
            "e_c_coef": 0.1217942976563666,
            "e_mean_degree": 3.034482758620689,
            "e_long_tail": 5.0
        },
        {
            "active_devs": 31.0,
            "num_commits": 1542.0,
            "num_files": 793.0,
            "num_emails": 171.0,
            "c_percentage": 0.632295719844358,
            "e_percentage": 0.5029239766081871,
            "inactive_c": 0.3103448275862069,
            "inactive_e": 0.1379310344827586,
            "c_nodes": 9.0,
            "c_edges": 14.0,
            "c_c_coef": 0.6185185185185185,
            "c_mean_degree": 3.111111111111111,
            "c_long_tail": 5.0,
            "e_nodes": 22.0,
            "e_edges": 34.0,
            "e_c_coef": 0.10508658008658,
            "e_mean_degree": 3.090909090909091,
            "e_long_tail": 7.0
        },
        {
            "active_devs": 44.0,
            "num_commits": 580.0,
            "num_files": 387.0,
            "num_emails": 174.0,
            "c_percentage": 0.6206896551724138,
            "e_percentage": 0.3793103448275862,
            "inactive_c": 0.4074074074074074,
            "inactive_e": 0.1034482758620689,
            "c_nodes": 6.0,
            "c_edges": 12.0,
            "c_c_coef": 0.8444444444444444,
            "c_mean_degree": 4.0,
            "c_long_tail": 4.0,
            "e_nodes": 37.0,
            "e_edges": 81.0,
            "e_c_coef": 0.1317772317772317,
            "e_mean_degree": 4.378378378378378,
            "e_long_tail": 10.0
        },
        {
            "active_devs": 33.0,
            "num_commits": 706.0,
            "num_files": 456.0,
            "num_emails": 111.0,
            "c_percentage": 0.4447592067988669,
            "e_percentage": 0.4414414414414414,
            "inactive_c": 0.2916666666666667,
            "inactive_e": 0.0344827586206896,
            "c_nodes": 7.0,
            "c_edges": 10.0,
            "c_c_coef": 0.7000000000000001,
            "c_mean_degree": 2.857142857142857,
            "c_long_tail": 4.0,
            "e_nodes": 28.0,
            "e_edges": 39.0,
            "e_c_coef": 0.2003968253968253,
            "e_mean_degree": 2.7857142857142856,
            "e_long_tail": 9.0
        },
        {
            "active_devs": 46.0,
            "num_commits": 1504.0,
            "num_files": 988.0,
            "num_emails": 278.0,
            "c_percentage": 0.7074468085106383,
            "e_percentage": 0.3489208633093525,
            "inactive_c": 0.5185185185185185,
            "inactive_e": 0.0,
            "c_nodes": 5.0,
            "c_edges": 10.0,
            "c_c_coef": 1.0,
            "c_mean_degree": 4.0,
            "c_long_tail": 0.0,
            "e_nodes": 42.0,
            "e_edges": 114.0,
            "e_c_coef": 0.3106396832237167,
            "e_mean_degree": 5.428571428571429,
            "e_long_tail": 16.0
        },
        {
            "active_devs": 52.0,
            "num_commits": 283.0,
            "num_files": 242.0,
            "num_emails": 397.0,
            "c_percentage": 0.2579505300353357,
            "e_percentage": 0.3476070528967254,
            "inactive_c": 0.4482758620689655,
            "inactive_e": 0.0344827586206896,
            "c_nodes": 11.0,
            "c_edges": 26.0,
            "c_c_coef": 0.677056277056277,
            "c_mean_degree": 4.727272727272728,
            "c_long_tail": 9.0,
            "e_nodes": 47.0,
            "e_edges": 137.0,
            "e_c_coef": 0.2582656114571008,
            "e_mean_degree": 5.829787234042553,
            "e_long_tail": 20.0
        },
        {
            "active_devs": 60.0,
            "num_commits": 416.0,
            "num_files": 292.0,
            "num_emails": 202.0,
            "c_percentage": 0.53125,
            "e_percentage": 0.3514851485148514,
            "inactive_c": 0.2307692307692307,
            "inactive_e": 0.1071428571428571,
            "c_nodes": 13.0,
            "c_edges": 23.0,
            "c_c_coef": 0.7020146520146521,
            "c_mean_degree": 3.5384615384615383,
            "c_long_tail": 6.0,
            "e_nodes": 44.0,
            "e_edges": 74.0,
            "e_c_coef": 0.181198347107438,
            "e_mean_degree": 3.363636363636364,
            "e_long_tail": 12.0
        },
        {
            "active_devs": 1.0,
            "num_commits": 0.0,
            "num_files": 0.0,
            "num_emails": 1.0,
            "c_percentage": 0.0,
            "e_percentage": 1.0,
            "inactive_c": 1.0,
            "inactive_e": 0.0,
            "c_nodes": 0.0,
            "c_edges": 0.0,
            "c_c_coef": 0.0,
            "c_mean_degree": 0.0,
            "c_long_tail": 0.0,
            "e_nodes": 2.0,
            "e_edges": 1.0,
            "e_c_coef": 0.0,
            "e_mean_degree": 1.0,
            "e_long_tail": 0.0
        }
    ]
}