{
    "project_id": "project_202",
    "status": "1",
    "history": [
        {
            "active_devs": -0.6877323420074349,
            "num_commits": -0.991177385661585,
            "num_files": -0.981036152356359,
            "num_emails": -0.88719438392641,
            "c_percentage": 0.2695214105793451,
            "e_percentage": -0.06437768240343344,
            "inactive_c": -0.14285714285714302,
            "inactive_e": -0.7931034482758622,
            "c_nodes": -0.9090909090909091,
            "c_edges": -0.9928057553956835,
            "c_c_coef": -1.0,
            "c_mean_degree": -0.9031007751937985,
            "c_long_tail": -1.0,
            "e_nodes": -0.6877323420074349,
            "e_edges": -0.8691019786910198,
            "e_c_coef": -0.3517805412763396,
            "e_mean_degree": -0.18502724472873744,
            "e_long_tail": -0.5757575757575757
        },
        {
            "active_devs": -0.6059479553903346,
            "num_commits": -0.9992666340726255,
            "num_files": -0.9992737249838606,
            "num_emails": -0.7114500121036069,
            "c_percentage": 0.2727272727272727,
            "e_percentage": 0.12416107382550345,
            "inactive_c": -0.41666666666666663,
            "inactive_e": -1.0,
            "c_nodes": -1.0,
            "c_edges": -1.0,
            "c_c_coef": -1.0,
            "c_mean_degree": -1.0,
            "c_long_tail": -1.0,
            "e_nodes": -0.5910780669144982,
            "e_edges": -0.771689497716895,
            "e_c_coef": -0.0992050950581772,
            "e_mean_degree": 0.08548168249660759,
            "e_long_tail": -0.09090909090909083
        },
        {
            "active_devs": -0.6431226765799256,
            "num_commits": -0.7125650028890174,
            "num_files": -0.6283892834086507,
            "num_emails": -0.44904381505688695,
            "c_percentage": 0.7719189732488017,
            "e_percentage": 0.08260105448154653,
            "inactive_c": -0.7647058823529412,
            "inactive_e": -1.0,
            "c_nodes": -0.5,
            "c_edges": -0.7913669064748201,
            "c_c_coef": 0.5337662337662337,
            "c_mean_degree": -0.48907681465821007,
            "c_long_tail": -0.33333333333333337,
            "e_nodes": -0.724907063197026,
            "e_edges": -0.7960426179604262,
            "e_c_coef": 0.06778438484320826,
            "e_mean_degree": 0.44144144144144115,
            "e_long_tail": -0.09090909090909083
        },
        {
            "active_devs": -0.6579925650557621,
            "num_commits": -0.9853993510822703,
            "num_files": -0.9784538411878632,
            "num_emails": -0.40643911885741957,
            "c_percentage": -0.06849315068493156,
            "e_percentage": 0.09624796084828713,
            "inactive_c": -0.7857142857142858,
            "inactive_e": -0.9310344827586208,
            "c_nodes": -0.7272727272727273,
            "c_edges": -0.9496402877697842,
            "c_c_coef": -0.2222222222222222,
            "c_mean_degree": -0.7739018087855298,
            "c_long_tail": -0.7037037037037037,
            "e_nodes": -0.7026022304832714,
            "e_edges": -0.8082191780821918,
            "e_c_coef": -0.20168506042647938,
            "e_mean_degree": 0.25373134328358193,
            "e_long_tail": -0.21212121212121215
        },
        {
            "active_devs": -0.6951672862453532,
            "num_commits": -0.9640872927685675,
            "num_files": -0.9164783731439639,
            "num_emails": -0.1900266279351247,
            "c_percentage": 0.4034653465346534,
            "e_percentage": 0.05917513448894196,
            "inactive_c": -0.7931034482758622,
            "inactive_e": -1.0,
            "c_nodes": -0.7272727272727273,
            "c_edges": -0.9568345323741008,
            "c_c_coef": -0.2777777777777778,
            "c_mean_degree": -0.8062015503875969,
            "c_long_tail": -0.7037037037037037,
            "e_nodes": -0.7174721189591078,
            "e_edges": -0.8006088280060883,
            "e_c_coef": -0.230640884743052,
            "e_mean_degree": 0.37208693375229096,
            "e_long_tail": 0.030303030303030276
        },
        {
            "active_devs": -0.5910780669144982,
            "num_commits": -0.9776878972398774,
            "num_files": -0.9505326016785023,
            "num_emails": -0.053982086661825246,
            "c_percentage": -0.13745019920318724,
            "e_percentage": 0.2896622313203685,
            "inactive_c": -0.7241379310344829,
            "inactive_e": -1.0,
            "c_nodes": -0.5909090909090908,
            "c_edges": -0.935251798561151,
            "c_c_coef": -0.6666666666666667,
            "c_mean_degree": -0.8062015503875969,
            "c_long_tail": -0.5555555555555556,
            "e_nodes": -0.6431226765799256,
            "e_edges": -0.7442922374429224,
            "e_c_coef": -0.1507631235452528,
            "e_mean_degree": 0.39303482587064664,
            "e_long_tail": -0.3939393939393939
        },
        {
            "active_devs": -0.5910780669144982,
            "num_commits": -0.9712431663629495,
            "num_files": -0.9316494512588767,
            "num_emails": -0.26119583635923505,
            "c_percentage": -0.26120556414219476,
            "e_percentage": 0.29619921363040635,
            "inactive_c": -0.7142857142857144,
            "inactive_e": -1.0,
            "c_nodes": -0.5909090909090908,
            "c_edges": -0.8992805755395683,
            "c_c_coef": 0.07407407407407418,
            "c_mean_degree": -0.698535745047373,
            "c_long_tail": -0.6296296296296297,
            "e_nodes": -0.6579925650557621,
            "e_edges": -0.7762557077625571,
            "e_c_coef": -0.2671436582779908,
            "e_mean_degree": 0.27190136275145993,
            "e_long_tail": -0.1515151515151515
        }
    ]
}