{
    "project_id": 308,
    "status": "0",
    "num_months": 27,
    "history": [
        {
            "month": 1.0,
            "active_devs": 3.0,
            "num_commits": 26.0,
            "num_files": 26.0,
            "num_emails": 4.0,
            "c_percentage": 1.0,
            "e_percentage": 0.5,
            "inactive_c": 0.0,
            "inactive_e": 0.8,
            "c_nodes": 0.0,
            "c_edges": 0.0,
            "c_c_coef": 0.0,
            "c_mean_degree": 0.0,
            "c_long_tail": 0.0,
            "e_nodes": 5.0,
            "e_edges": 3.0,
            "e_c_coef": 0.0,
            "e_mean_degree": 1.2,
            "e_long_tail": 1.0
        },
        {
            "month": 2.0,
            "active_devs": 17.0,
            "num_commits": 942.0,
            "num_files": 447.0,
            "num_emails": 34.0,
            "c_percentage": 0.6645435244161358,
            "e_percentage": 0.3529411764705882,
            "inactive_c": 0.2142857142857142,
            "inactive_e": 0.3214285714285714,
            "c_nodes": 4.0,
            "c_edges": 6.0,
            "c_c_coef": 1.0,
            "c_mean_degree": 3.0,
            "c_long_tail": 0.0,
            "e_nodes": 14.0,
            "e_edges": 15.0,
            "e_c_coef": 0.0,
            "e_mean_degree": 2.142857142857143,
            "e_long_tail": 5.0
        },
        {
            "month": 3.0,
            "active_devs": 10.0,
            "num_commits": 486.0,
            "num_files": 199.0,
            "num_emails": 17.0,
            "c_percentage": 0.8189300411522634,
            "e_percentage": 0.2941176470588235,
            "inactive_c": 0.074074074074074,
            "inactive_e": 0.6538461538461539,
            "c_nodes": 3.0,
            "c_edges": 2.0,
            "c_c_coef": 0.0,
            "c_mean_degree": 1.3333333333333333,
            "c_long_tail": 1.0,
            "e_nodes": 9.0,
            "e_edges": 10.0,
            "e_c_coef": 0.2592592592592592,
            "e_mean_degree": 2.2222222222222223,
            "e_long_tail": 3.0
        },
        {
            "month": 4.0,
            "active_devs": 13.0,
            "num_commits": 444.0,
            "num_files": 193.0,
            "num_emails": 55.0,
            "c_percentage": 0.5315315315315315,
            "e_percentage": 0.3090909090909091,
            "inactive_c": 0.1034482758620689,
            "inactive_e": 0.3214285714285714,
            "c_nodes": 2.0,
            "c_edges": 1.0,
            "c_c_coef": 0.0,
            "c_mean_degree": 1.0,
            "c_long_tail": 0.0,
            "e_nodes": 12.0,
            "e_edges": 20.0,
            "e_c_coef": 0.4444444444444445,
            "e_mean_degree": 3.333333333333333,
            "e_long_tail": 8.0
        },
        {
            "month": 5.0,
            "active_devs": 6.0,
            "num_commits": 470.0,
            "num_files": 229.0,
            "num_emails": 13.0,
            "c_percentage": 0.6404255319148936,
            "e_percentage": 0.6153846153846154,
            "inactive_c": 0.1379310344827586,
            "inactive_e": 0.7857142857142857,
            "c_nodes": 3.0,
            "c_edges": 2.0,
            "c_c_coef": 0.0,
            "c_mean_degree": 1.3333333333333333,
            "c_long_tail": 1.0,
            "e_nodes": 6.0,
            "e_edges": 6.0,
            "e_c_coef": 0.0,
            "e_mean_degree": 2.0,
            "e_long_tail": 2.0
        },
        {
            "month": 6.0,
            "active_devs": 20.0,
            "num_commits": 615.0,
            "num_files": 297.0,
            "num_emails": 368.0,
            "c_percentage": 0.4504065040650406,
            "e_percentage": 0.782608695652174,
            "inactive_c": 0.2142857142857142,
            "inactive_e": 0.0476190476190476,
            "c_nodes": 3.0,
            "c_edges": 3.0,
            "c_c_coef": 1.0,
            "c_mean_degree": 2.0,
            "c_long_tail": 0.0,
            "e_nodes": 21.0,
            "e_edges": 40.0,
            "e_c_coef": 0.2355631141345426,
            "e_mean_degree": 3.809523809523809,
            "e_long_tail": 9.0
        },
        {
            "month": 7.0,
            "active_devs": 18.0,
            "num_commits": 553.0,
            "num_files": 269.0,
            "num_emails": 395.0,
            "c_percentage": 0.5424954792043399,
            "e_percentage": 0.4607594936708861,
            "inactive_c": 0.0689655172413793,
            "inactive_e": 0.0,
            "c_nodes": 3.0,
            "c_edges": 3.0,
            "c_c_coef": 1.0,
            "c_mean_degree": 2.0,
            "c_long_tail": 0.0,
            "e_nodes": 20.0,
            "e_edges": 40.0,
            "e_c_coef": 0.29504329004329,
            "e_mean_degree": 4.0,
            "e_long_tail": 8.0
        },
        {
            "month": 8.0,
            "active_devs": 12.0,
            "num_commits": 193.0,
            "num_files": 119.0,
            "num_emails": 190.0,
            "c_percentage": 0.4766839378238341,
            "e_percentage": 0.5473684210526316,
            "inactive_c": 0.391304347826087,
            "inactive_e": 0.3214285714285714,
            "c_nodes": 3.0,
            "c_edges": 3.0,
            "c_c_coef": 1.0,
            "c_mean_degree": 2.0,
            "c_long_tail": 0.0,
            "e_nodes": 12.0,
            "e_edges": 24.0,
            "e_c_coef": 0.3599206349206349,
            "e_mean_degree": 4.0,
            "e_long_tail": 5.0
        },
        {
            "month": 9.0,
            "active_devs": 22.0,
            "num_commits": 862.0,
            "num_files": 408.0,
            "num_emails": 285.0,
            "c_percentage": 0.4976798143851508,
            "e_percentage": 0.5614035087719298,
            "inactive_c": 0.1923076923076923,
            "inactive_e": 0.0689655172413793,
            "c_nodes": 4.0,
            "c_edges": 6.0,
            "c_c_coef": 1.0,
            "c_mean_degree": 3.0,
            "c_long_tail": 0.0,
            "e_nodes": 20.0,
            "e_edges": 49.0,
            "e_c_coef": 0.5238217338217338,
            "e_mean_degree": 4.9,
            "e_long_tail": 9.0
        },
        {
            "month": 10.0,
            "active_devs": 18.0,
            "num_commits": 682.0,
            "num_files": 503.0,
            "num_emails": 114.0,
            "c_percentage": 0.8577712609970675,
            "e_percentage": 0.4385964912280701,
            "inactive_c": 0.16,
            "inactive_e": 0.04,
            "c_nodes": 2.0,
            "c_edges": 1.0,
            "c_c_coef": 0.0,
            "c_mean_degree": 1.0,
            "c_long_tail": 0.0,
            "e_nodes": 19.0,
            "e_edges": 30.0,
            "e_c_coef": 0.2238095238095238,
            "e_mean_degree": 3.1578947368421053,
            "e_long_tail": 6.0
        },
        {
            "month": 11.0,
            "active_devs": 16.0,
            "num_commits": 102.0,
            "num_files": 63.0,
            "num_emails": 306.0,
            "c_percentage": 0.6568627450980392,
            "e_percentage": 0.6372549019607843,
            "inactive_c": 0.1034482758620689,
            "inactive_e": 0.1724137931034483,
            "c_nodes": 2.0,
            "c_edges": 1.0,
            "c_c_coef": 0.0,
            "c_mean_degree": 1.0,
            "c_long_tail": 0.0,
            "e_nodes": 19.0,
            "e_edges": 37.0,
            "e_c_coef": 0.3522480443533075,
            "e_mean_degree": 3.8947368421052633,
            "e_long_tail": 6.0
        },
        {
            "month": 12.0,
            "active_devs": 17.0,
            "num_commits": 117.0,
            "num_files": 53.0,
            "num_emails": 307.0,
            "c_percentage": 0.7094017094017094,
            "e_percentage": 0.5179153094462541,
            "inactive_c": 0.0689655172413793,
            "inactive_e": 0.0689655172413793,
            "c_nodes": 2.0,
            "c_edges": 1.0,
            "c_c_coef": 0.0,
            "c_mean_degree": 1.0,
            "c_long_tail": 0.0,
            "e_nodes": 16.0,
            "e_edges": 36.0,
            "e_c_coef": 0.3895833333333333,
            "e_mean_degree": 4.5,
            "e_long_tail": 6.0
        },
        {
            "month": 13.0,
            "active_devs": 9.0,
            "num_commits": 69.0,
            "num_files": 31.0,
            "num_emails": 124.0,
            "c_percentage": 0.5652173913043478,
            "e_percentage": 0.4032258064516129,
            "inactive_c": 0.3571428571428571,
            "inactive_e": 0.2307692307692307,
            "c_nodes": 2.0,
            "c_edges": 1.0,
            "c_c_coef": 0.0,
            "c_mean_degree": 1.0,
            "c_long_tail": 0.0,
            "e_nodes": 9.0,
            "e_edges": 16.0,
            "e_c_coef": 0.3862433862433863,
            "e_mean_degree": 3.555555555555556,
            "e_long_tail": 3.0
        },
        {
            "month": 14.0,
            "active_devs": 10.0,
            "num_commits": 192.0,
            "num_files": 114.0,
            "num_emails": 42.0,
            "c_percentage": 0.5520833333333334,
            "e_percentage": 0.3809523809523809,
            "inactive_c": 0.1923076923076923,
            "inactive_e": 0.3846153846153846,
            "c_nodes": 3.0,
            "c_edges": 2.0,
            "c_c_coef": 0.0,
            "c_mean_degree": 1.3333333333333333,
            "c_long_tail": 1.0,
            "e_nodes": 10.0,
            "e_edges": 13.0,
            "e_c_coef": 0.2066666666666666,
            "e_mean_degree": 2.6,
            "e_long_tail": 4.0
        },
        {
            "month": 15.0,
            "active_devs": 6.0,
            "num_commits": 15.0,
            "num_files": 14.0,
            "num_emails": 15.0,
            "c_percentage": 1.0,
            "e_percentage": 0.4,
            "inactive_c": 0.65,
            "inactive_e": 0.5357142857142857,
            "c_nodes": 0.0,
            "c_edges": 0.0,
            "c_c_coef": 0.0,
            "c_mean_degree": 0.0,
            "c_long_tail": 0.0,
            "e_nodes": 5.0,
            "e_edges": 4.0,
            "e_c_coef": 0.0,
            "e_mean_degree": 1.6,
            "e_long_tail": 2.0
        },
        {
            "month": 16.0,
            "active_devs": 5.0,
            "num_commits": 93.0,
            "num_files": 57.0,
            "num_emails": 7.0,
            "c_percentage": 0.7096774193548387,
            "e_percentage": 0.8571428571428571,
            "inactive_c": 0.4117647058823529,
            "inactive_e": 0.8823529411764706,
            "c_nodes": 0.0,
            "c_edges": 0.0,
            "c_c_coef": 0.0,
            "c_mean_degree": 0.0,
            "c_long_tail": 0.0,
            "e_nodes": 3.0,
            "e_edges": 2.0,
            "e_c_coef": 0.0,
            "e_mean_degree": 1.3333333333333333,
            "e_long_tail": 1.0
        },
        {
            "month": 17.0,
            "active_devs": 3.0,
            "num_commits": 53.0,
            "num_files": 37.0,
            "num_emails": 4.0,
            "c_percentage": 0.9245283018867924,
            "e_percentage": 1.0,
            "inactive_c": 0.4583333333333333,
            "inactive_e": 0.0,
            "c_nodes": 0.0,
            "c_edges": 0.0,
            "c_c_coef": 0.0,
            "c_mean_degree": 0.0,
            "c_long_tail": 0.0,
            "e_nodes": 2.0,
            "e_edges": 2.0,
            "e_c_coef": 0.0,
            "e_mean_degree": 2.0,
            "e_long_tail": 1.0
        },
        {
            "month": 18.0,
            "active_devs": 6.0,
            "num_commits": 24.0,
            "num_files": 16.0,
            "num_emails": 76.0,
            "c_percentage": 0.9166666666666666,
            "e_percentage": 0.7368421052631579,
            "inactive_c": 0.6818181818181818,
            "inactive_e": 0.2857142857142857,
            "c_nodes": 2.0,
            "c_edges": 1.0,
            "c_c_coef": 0.0,
            "c_mean_degree": 1.0,
            "c_long_tail": 0.0,
            "e_nodes": 6.0,
            "e_edges": 10.0,
            "e_c_coef": 0.4777777777777778,
            "e_mean_degree": 3.333333333333333,
            "e_long_tail": 3.0
        },
        {
            "month": 19.0,
            "active_devs": 5.0,
            "num_commits": 4.0,
            "num_files": 3.0,
            "num_emails": 29.0,
            "c_percentage": 1.0,
            "e_percentage": 0.7241379310344828,
            "inactive_c": 0.0,
            "inactive_e": 0.3703703703703703,
            "c_nodes": 0.0,
            "c_edges": 0.0,
            "c_c_coef": 0.0,
            "c_mean_degree": 0.0,
            "c_long_tail": 0.0,
            "e_nodes": 4.0,
            "e_edges": 3.0,
            "e_c_coef": 0.0,
            "e_mean_degree": 1.5,
            "e_long_tail": 1.0
        },
        {
            "month": 20.0,
            "active_devs": 4.0,
            "num_commits": 5.0,
            "num_files": 5.0,
            "num_emails": 44.0,
            "c_percentage": 1.0,
            "e_percentage": 0.9318181818181818,
            "inactive_c": 0.9629629629629628,
            "inactive_e": 0.6428571428571429,
            "c_nodes": 0.0,
            "c_edges": 0.0,
            "c_c_coef": 0.0,
            "c_mean_degree": 0.0,
            "c_long_tail": 0.0,
            "e_nodes": 10.0,
            "e_edges": 10.0,
            "e_c_coef": 0.0,
            "e_mean_degree": 2.0,
            "e_long_tail": 1.0
        },
        {
            "month": 21.0,
            "active_devs": 11.0,
            "num_commits": 17.0,
            "num_files": 14.0,
            "num_emails": 80.0,
            "c_percentage": 1.0,
            "e_percentage": 0.45,
            "inactive_c": 0.3636363636363636,
            "inactive_e": 0.1666666666666666,
            "c_nodes": 0.0,
            "c_edges": 0.0,
            "c_c_coef": 0.0,
            "c_mean_degree": 0.0,
            "c_long_tail": 0.0,
            "e_nodes": 10.0,
            "e_edges": 17.0,
            "e_c_coef": 0.4066666666666666,
            "e_mean_degree": 3.4,
            "e_long_tail": 5.0
        },
        {
            "month": 22.0,
            "active_devs": 10.0,
            "num_commits": 5.0,
            "num_files": 4.0,
            "num_emails": 62.0,
            "c_percentage": 0.8,
            "e_percentage": 0.3709677419354839,
            "inactive_c": 0.9523809523809524,
            "inactive_e": 0.3076923076923077,
            "c_nodes": 0.0,
            "c_edges": 0.0,
            "c_c_coef": 0.0,
            "c_mean_degree": 0.0,
            "c_long_tail": 0.0,
            "e_nodes": 9.0,
            "e_edges": 17.0,
            "e_c_coef": 0.3592592592592593,
            "e_mean_degree": 3.7777777777777777,
            "e_long_tail": 5.0
        },
        {
            "month": 23.0,
            "active_devs": 10.0,
            "num_commits": 9.0,
            "num_files": 6.0,
            "num_emails": 32.0,
            "c_percentage": 1.0,
            "e_percentage": 0.46875,
            "inactive_c": 0.8235294117647058,
            "inactive_e": 0.3461538461538461,
            "c_nodes": 0.0,
            "c_edges": 0.0,
            "c_c_coef": 0.0,
            "c_mean_degree": 0.0,
            "c_long_tail": 0.0,
            "e_nodes": 9.0,
            "e_edges": 10.0,
            "e_c_coef": 0.0,
            "e_mean_degree": 2.2222222222222223,
            "e_long_tail": 3.0
        },
        {
            "month": 24.0,
            "active_devs": 2.0,
            "num_commits": 0.0,
            "num_files": 0.0,
            "num_emails": 8.0,
            "c_percentage": 0.0,
            "e_percentage": 0.625,
            "inactive_c": 1.0,
            "inactive_e": 0.8666666666666667,
            "c_nodes": 0.0,
            "c_edges": 0.0,
            "c_c_coef": 0.0,
            "c_mean_degree": 0.0,
            "c_long_tail": 0.0,
            "e_nodes": 2.0,
            "e_edges": 3.0,
            "e_c_coef": 0.0,
            "e_mean_degree": 3.0,
            "e_long_tail": 0.0
        },
        {
            "month": 25.0,
            "active_devs": 0.0,
            "num_commits": 0.0,
            "num_files": 0.0,
            "num_emails": 0.0,
            "c_percentage": 0.0,
            "e_percentage": 0.0,
            "inactive_c": 1.0,
            "inactive_e": 1.0,
            "c_nodes": 0.0,
            "c_edges": 0.0,
            "c_c_coef": 0.0,
            "c_mean_degree": 0.0,
            "c_long_tail": 0.0,
            "e_nodes": 0.0,
            "e_edges": 0.0,
            "e_c_coef": 0.0,
            "e_mean_degree": 0.0,
            "e_long_tail": 0.0
        },
        {
            "month": 26.0,
            "active_devs": 0.0,
            "num_commits": 0.0,
            "num_files": 0.0,
            "num_emails": 0.0,
            "c_percentage": 0.0,
            "e_percentage": 0.0,
            "inactive_c": 1.0,
            "inactive_e": 1.0,
            "c_nodes": 0.0,
            "c_edges": 0.0,
            "c_c_coef": 0.0,
            "c_mean_degree": 0.0,
            "c_long_tail": 0.0,
            "e_nodes": 0.0,
            "e_edges": 0.0,
            "e_c_coef": 0.0,
            "e_mean_degree": 0.0,
            "e_long_tail": 0.0
        },
        {
            "month": 27.0,
            "active_devs": 2.0,
            "num_commits": 0.0,
            "num_files": 0.0,
            "num_emails": 3.0,
            "c_percentage": 0.0,
            "e_percentage": 0.6666666666666666,
            "inactive_c": 1.0,
            "inactive_e": 0.8,
            "c_nodes": 0.0,
            "c_edges": 0.0,
            "c_c_coef": 0.0,
            "c_mean_degree": 0.0,
            "c_long_tail": 0.0,
            "e_nodes": 2.0,
            "e_edges": 1.0,
            "e_c_coef": 0.0,
            "e_mean_degree": 1.0,
            "e_long_tail": 0.0
        }
    ]
}