{
    "project_id": 80,
    "status": "1",
    "num_months": 17,
    "history": [
        {
            "month": 1.0,
            "active_devs": 2.0,
            "num_commits": 0.0,
            "num_files": 0.0,
            "num_emails": 3.0,
            "c_percentage": 0.0,
            "e_percentage": 0.6666666666666666,
            "inactive_c": 1.0,
            "inactive_e": 0.5,
            "c_nodes": 0.0,
            "c_edges": 0.0,
            "c_c_coef": 0.0,
            "c_mean_degree": 0.0,
            "c_long_tail": 0.0,
            "e_nodes": 2.0,
            "e_edges": 1.0,
            "e_c_coef": 0.0,
            "e_mean_degree": 1.0,
            "e_long_tail": 0.0
        },
        {
            "month": 2.0,
            "active_devs": 5.0,
            "num_commits": 0.0,
            "num_files": 0.0,
            "num_emails": 14.0,
            "c_percentage": 0.0,
            "e_percentage": 0.6428571428571429,
            "inactive_c": 1.0,
            "inactive_e": 0.6153846153846154,
            "c_nodes": 0.0,
            "c_edges": 0.0,
            "c_c_coef": 0.0,
            "c_mean_degree": 0.0,
            "c_long_tail": 0.0,
            "e_nodes": 5.0,
            "e_edges": 5.0,
            "e_c_coef": 0.0,
            "e_mean_degree": 2.0,
            "e_long_tail": 1.0
        },
        {
            "month": 3.0,
            "active_devs": 6.0,
            "num_commits": 0.0,
            "num_files": 0.0,
            "num_emails": 46.0,
            "c_percentage": 0.0,
            "e_percentage": 0.6086956521739131,
            "inactive_c": 1.0,
            "inactive_e": 0.2222222222222222,
            "c_nodes": 0.0,
            "c_edges": 0.0,
            "c_c_coef": 0.0,
            "c_mean_degree": 0.0,
            "c_long_tail": 0.0,
            "e_nodes": 6.0,
            "e_edges": 6.0,
            "e_c_coef": 0.0,
            "e_mean_degree": 2.0,
            "e_long_tail": 1.0
        },
        {
            "month": 4.0,
            "active_devs": 10.0,
            "num_commits": 4.0,
            "num_files": 4.0,
            "num_emails": 51.0,
            "c_percentage": 1.0,
            "e_percentage": 0.4901960784313725,
            "inactive_c": 0.0,
            "inactive_e": 0.1052631578947368,
            "c_nodes": 0.0,
            "c_edges": 0.0,
            "c_c_coef": 0.0,
            "c_mean_degree": 0.0,
            "c_long_tail": 0.0,
            "e_nodes": 9.0,
            "e_edges": 12.0,
            "e_c_coef": 0.5304232804232805,
            "e_mean_degree": 2.6666666666666665,
            "e_long_tail": 1.0
        },
        {
            "month": 5.0,
            "active_devs": 11.0,
            "num_commits": 654.0,
            "num_files": 499.0,
            "num_emails": 64.0,
            "c_percentage": 1.0,
            "e_percentage": 0.453125,
            "inactive_c": 0.1785714285714285,
            "inactive_e": 0.3214285714285714,
            "c_nodes": 0.0,
            "c_edges": 0.0,
            "c_c_coef": 0.0,
            "c_mean_degree": 0.0,
            "c_long_tail": 0.0,
            "e_nodes": 10.0,
            "e_edges": 15.0,
            "e_c_coef": 0.3638095238095238,
            "e_mean_degree": 3.0,
            "e_long_tail": 3.0
        },
        {
            "month": 6.0,
            "active_devs": 10.0,
            "num_commits": 807.0,
            "num_files": 582.0,
            "num_emails": 65.0,
            "c_percentage": 0.8116480793060719,
            "e_percentage": 0.5692307692307692,
            "inactive_c": 0.1428571428571428,
            "inactive_e": 0.4074074074074074,
            "c_nodes": 2.0,
            "c_edges": 1.0,
            "c_c_coef": 0.0,
            "c_mean_degree": 1.0,
            "c_long_tail": 0.0,
            "e_nodes": 9.0,
            "e_edges": 10.0,
            "e_c_coef": 0.0,
            "e_mean_degree": 2.2222222222222223,
            "e_long_tail": 1.0
        },
        {
            "month": 7.0,
            "active_devs": 10.0,
            "num_commits": 63.0,
            "num_files": 34.0,
            "num_emails": 63.0,
            "c_percentage": 1.0,
            "e_percentage": 0.5238095238095238,
            "inactive_c": 0.3076923076923077,
            "inactive_e": 0.4482758620689655,
            "c_nodes": 0.0,
            "c_edges": 0.0,
            "c_c_coef": 0.0,
            "c_mean_degree": 0.0,
            "c_long_tail": 0.0,
            "e_nodes": 10.0,
            "e_edges": 14.0,
            "e_c_coef": 0.2722222222222222,
            "e_mean_degree": 2.8,
            "e_long_tail": 1.0
        },
        {
            "month": 8.0,
            "active_devs": 14.0,
            "num_commits": 140.0,
            "num_files": 63.0,
            "num_emails": 121.0,
            "c_percentage": 0.9428571428571428,
            "e_percentage": 0.6033057851239669,
            "inactive_c": 0.1034482758620689,
            "inactive_e": 0.1379310344827586,
            "c_nodes": 2.0,
            "c_edges": 1.0,
            "c_c_coef": 0.0,
            "c_mean_degree": 1.0,
            "c_long_tail": 0.0,
            "e_nodes": 12.0,
            "e_edges": 20.0,
            "e_c_coef": 0.3129629629629629,
            "e_mean_degree": 3.333333333333333,
            "e_long_tail": 3.0
        },
        {
            "month": 9.0,
            "active_devs": 21.0,
            "num_commits": 178.0,
            "num_files": 103.0,
            "num_emails": 136.0,
            "c_percentage": 0.7247191011235955,
            "e_percentage": 0.5147058823529411,
            "inactive_c": 0.1724137931034483,
            "inactive_e": 0.1379310344827586,
            "c_nodes": 3.0,
            "c_edges": 3.0,
            "c_c_coef": 1.0,
            "c_mean_degree": 2.0,
            "c_long_tail": 0.0,
            "e_nodes": 19.0,
            "e_edges": 30.0,
            "e_c_coef": 0.2745614035087719,
            "e_mean_degree": 3.1578947368421053,
            "e_long_tail": 3.0
        },
        {
            "month": 10.0,
            "active_devs": 15.0,
            "num_commits": 215.0,
            "num_files": 140.0,
            "num_emails": 198.0,
            "c_percentage": 0.5302325581395348,
            "e_percentage": 0.4898989898989899,
            "inactive_c": 0.2068965517241379,
            "inactive_e": 0.1071428571428571,
            "c_nodes": 3.0,
            "c_edges": 2.0,
            "c_c_coef": 0.0,
            "c_mean_degree": 1.3333333333333333,
            "c_long_tail": 1.0,
            "e_nodes": 14.0,
            "e_edges": 27.0,
            "e_c_coef": 0.3928571428571428,
            "e_mean_degree": 3.857142857142857,
            "e_long_tail": 4.0
        },
        {
            "month": 11.0,
            "active_devs": 8.0,
            "num_commits": 407.0,
            "num_files": 241.0,
            "num_emails": 127.0,
            "c_percentage": 0.5577395577395577,
            "e_percentage": 0.3858267716535433,
            "inactive_c": 0.0,
            "inactive_e": 0.0,
            "c_nodes": 2.0,
            "c_edges": 1.0,
            "c_c_coef": 0.0,
            "c_mean_degree": 1.0,
            "c_long_tail": 0.0,
            "e_nodes": 8.0,
            "e_edges": 16.0,
            "e_c_coef": 0.5125,
            "e_mean_degree": 4.0,
            "e_long_tail": 5.0
        },
        {
            "month": 12.0,
            "active_devs": 16.0,
            "num_commits": 301.0,
            "num_files": 205.0,
            "num_emails": 152.0,
            "c_percentage": 0.5182724252491694,
            "e_percentage": 0.743421052631579,
            "inactive_c": 0.0689655172413793,
            "inactive_e": 0.0689655172413793,
            "c_nodes": 2.0,
            "c_edges": 1.0,
            "c_c_coef": 0.0,
            "c_mean_degree": 1.0,
            "c_long_tail": 0.0,
            "e_nodes": 14.0,
            "e_edges": 22.0,
            "e_c_coef": 0.3664835164835165,
            "e_mean_degree": 3.142857142857143,
            "e_long_tail": 2.0
        },
        {
            "month": 13.0,
            "active_devs": 10.0,
            "num_commits": 274.0,
            "num_files": 202.0,
            "num_emails": 59.0,
            "c_percentage": 0.572992700729927,
            "e_percentage": 0.4745762711864407,
            "inactive_c": 0.238095238095238,
            "inactive_e": 0.3846153846153846,
            "c_nodes": 3.0,
            "c_edges": 2.0,
            "c_c_coef": 0.0,
            "c_mean_degree": 1.3333333333333333,
            "c_long_tail": 1.0,
            "e_nodes": 8.0,
            "e_edges": 12.0,
            "e_c_coef": 0.2559523809523809,
            "e_mean_degree": 3.0,
            "e_long_tail": 2.0
        },
        {
            "month": 14.0,
            "active_devs": 7.0,
            "num_commits": 14.0,
            "num_files": 13.0,
            "num_emails": 32.0,
            "c_percentage": 0.5714285714285714,
            "e_percentage": 0.34375,
            "inactive_c": 0.8571428571428571,
            "inactive_e": 0.5185185185185185,
            "c_nodes": 0.0,
            "c_edges": 0.0,
            "c_c_coef": 0.0,
            "c_mean_degree": 0.0,
            "c_long_tail": 0.0,
            "e_nodes": 6.0,
            "e_edges": 8.0,
            "e_c_coef": 0.0,
            "e_mean_degree": 2.6666666666666665,
            "e_long_tail": 5.0
        },
        {
            "month": 15.0,
            "active_devs": 10.0,
            "num_commits": 24.0,
            "num_files": 15.0,
            "num_emails": 34.0,
            "c_percentage": 1.0,
            "e_percentage": 0.4411764705882353,
            "inactive_c": 0.6071428571428571,
            "inactive_e": 0.6551724137931034,
            "c_nodes": 0.0,
            "c_edges": 0.0,
            "c_c_coef": 0.0,
            "c_mean_degree": 0.0,
            "c_long_tail": 0.0,
            "e_nodes": 10.0,
            "e_edges": 13.0,
            "e_c_coef": 0.0,
            "e_mean_degree": 2.6,
            "e_long_tail": 4.0
        },
        {
            "month": 16.0,
            "active_devs": 11.0,
            "num_commits": 68.0,
            "num_files": 48.0,
            "num_emails": 65.0,
            "c_percentage": 1.0,
            "e_percentage": 0.5230769230769231,
            "inactive_c": 0.16,
            "inactive_e": 0.2592592592592592,
            "c_nodes": 0.0,
            "c_edges": 0.0,
            "c_c_coef": 0.0,
            "c_mean_degree": 0.0,
            "c_long_tail": 0.0,
            "e_nodes": 10.0,
            "e_edges": 14.0,
            "e_c_coef": 0.2035714285714285,
            "e_mean_degree": 2.8,
            "e_long_tail": 2.0
        },
        {
            "month": 17.0,
            "active_devs": 5.0,
            "num_commits": 4.0,
            "num_files": 4.0,
            "num_emails": 9.0,
            "c_percentage": 1.0,
            "e_percentage": 0.5555555555555556,
            "inactive_c": 0.0,
            "inactive_e": 0.3333333333333333,
            "c_nodes": 0.0,
            "c_edges": 0.0,
            "c_c_coef": 0.0,
            "c_mean_degree": 0.0,
            "c_long_tail": 0.0,
            "e_nodes": 5.0,
            "e_edges": 4.0,
            "e_c_coef": 0.0,
            "e_mean_degree": 1.6,
            "e_long_tail": 1.0
        }
    ]
}