{
    "project_id": "project_56",
    "status": "1",
    "history": [
        {
            "active_devs": -0.828996282527881,
            "num_commits": -0.9882216987421664,
            "num_files": -0.9837798579728857,
            "num_emails": -0.9612684580004841,
            "c_percentage": 0.7660377358490567,
            "e_percentage": 0.07499999999999996,
            "inactive_c": 0.07692307692307687,
            "inactive_e": -0.07692307692307698,
            "c_nodes": -0.8636363636363636,
            "c_edges": -0.9797297297297297,
            "c_c_coef": 1.0,
            "c_mean_degree": -0.8062015503875969,
            "c_long_tail": -1.0,
            "e_nodes": -0.8438661710037174,
            "e_edges": -0.9634703196347032,
            "e_c_coef": -0.8383838383838385,
            "e_mean_degree": -0.5451314854299929,
            "e_long_tail": -0.8787878787878788
        },
        {
            "active_devs": -0.79182156133829,
            "num_commits": -0.9961109382639228,
            "num_files": -0.9919302775984506,
            "num_emails": -0.9467441297506657,
            "c_percentage": -0.1885714285714286,
            "e_percentage": -0.07272727272727275,
            "inactive_c": -0.18518518518518523,
            "inactive_e": -0.8571428571428572,
            "c_nodes": -0.6818181818181819,
            "c_edges": -0.9324324324324325,
            "c_c_coef": -0.09523809523809523,
            "c_mean_degree": -0.7231450719822813,
            "c_long_tail": -0.6428571428571429,
            "e_nodes": -0.8364312267657993,
            "e_edges": -0.9589041095890412,
            "e_c_coef": -0.8151515151515152,
            "e_mean_degree": -0.5115332428765265,
            "e_long_tail": -0.4545454545454546
        },
        {
            "active_devs": -0.6802973977695168,
            "num_commits": -0.9917996355393573,
            "num_files": -0.9752259522272434,
            "num_emails": -0.9312515129508594,
            "c_percentage": 0.4037940379403795,
            "e_percentage": -0.38028169014084523,
            "inactive_c": -0.3793103448275862,
            "inactive_e": -0.7931034482758622,
            "c_nodes": -0.6363636363636364,
            "c_edges": -0.9256756756756757,
            "c_c_coef": -2.220446049250313e-16,
            "c_mean_degree": -0.7335271317829457,
            "c_long_tail": -0.5714285714285714,
            "e_nodes": -0.7472118959107807,
            "e_edges": -0.9117199391171994,
            "e_c_coef": -0.757983193277311,
            "e_mean_degree": -0.3210418495756513,
            "e_long_tail": 0.2727272727272727
        },
        {
            "active_devs": -0.7323420074349443,
            "num_commits": -0.9934441530734699,
            "num_files": -0.9823273079406069,
            "num_emails": -0.9191479060760106,
            "c_percentage": -0.3830508474576272,
            "e_percentage": -0.2095808383233534,
            "inactive_c": -0.3571428571428572,
            "inactive_e": -0.6551724137931034,
            "c_nodes": -0.5909090909090908,
            "c_edges": -0.8378378378378378,
            "c_c_coef": 0.5492063492063493,
            "c_mean_degree": -0.4832041343669251,
            "c_long_tail": -0.4285714285714286,
            "e_nodes": -0.7843866171003717,
            "e_edges": -0.9299847792998478,
            "e_c_coef": -0.567049808429119,
            "e_mean_degree": -0.3686738720192143,
            "e_long_tail": -0.33333333333333326
        },
        {
            "active_devs": -0.7323420074349443,
            "num_commits": -0.9980888039468421,
            "num_files": -0.9938670109748224,
            "num_emails": -0.9457758412006778,
            "c_percentage": -0.5348837209302326,
            "e_percentage": -0.1964285714285714,
            "inactive_c": -0.16666666666666663,
            "inactive_e": -0.7857142857142858,
            "c_nodes": -0.7272727272727273,
            "c_edges": -0.8986486486486487,
            "c_c_coef": 1.0,
            "c_mean_degree": -0.5155038759689923,
            "c_long_tail": -1.0,
            "e_nodes": -0.7992565055762082,
            "e_edges": -0.943683409436834,
            "e_c_coef": -0.5216931216931218,
            "e_mean_degree": -0.4545789570665193,
            "e_long_tail": -0.33333333333333326
        },
        {
            "active_devs": -0.7992565055762082,
            "num_commits": -0.9887328325703365,
            "num_files": -0.9638476436410588,
            "num_emails": -0.952553861050593,
            "c_percentage": 0.5266272189349113,
            "e_percentage": -0.326530612244898,
            "inactive_c": -0.31034482758620685,
            "inactive_e": -0.44827586206896564,
            "c_nodes": -0.8181818181818181,
            "c_edges": -0.9662162162162162,
            "c_c_coef": 0.6666666666666665,
            "c_mean_degree": -0.7577519379844961,
            "c_long_tail": -0.8571428571428572,
            "e_nodes": -0.8215613382899628,
            "e_edges": -0.93455098934551,
            "e_c_coef": -0.7131313131313133,
            "e_mean_degree": -0.28689883913764525,
            "e_long_tail": -0.33333333333333326
        },
        {
            "active_devs": -0.8141263940520447,
            "num_commits": -0.996622072092093,
            "num_files": -0.9888637830858619,
            "num_emails": -0.981118373275236,
            "c_percentage": -0.11842105263157898,
            "e_percentage": -0.3846153846153846,
            "inactive_c": -0.2857142857142858,
            "inactive_e": -0.2727272727272728,
            "c_nodes": -0.7727272727272727,
            "c_edges": -0.9594594594594594,
            "c_c_coef": 0.7333333333333332,
            "c_mean_degree": -0.7674418604651163,
            "c_long_tail": -0.9285714285714286,
            "e_nodes": -0.8587360594795539,
            "e_edges": -0.9726027397260274,
            "e_c_coef": -0.5087719298245617,
            "e_mean_degree": -0.6229379418695995,
            "e_long_tail": -0.8181818181818181
        },
        {
            "active_devs": -0.8438661710037174,
            "num_commits": -0.9980443575270012,
            "num_files": -0.9942704970948999,
            "num_emails": -0.9878963931251513,
            "c_percentage": -0.36363636363636365,
            "e_percentage": -0.36,
            "inactive_c": -0.4736842105263158,
            "inactive_e": -0.2142857142857144,
            "c_nodes": -0.6363636363636364,
            "c_edges": -0.9391891891891891,
            "c_c_coef": 0.050000000000000044,
            "c_mean_degree": -0.7819767441860466,
            "c_long_tail": -0.8571428571428572,
            "e_nodes": -0.9182156133828996,
            "e_edges": -0.9863013698630136,
            "e_c_coef": -1.0,
            "e_mean_degree": -0.6743554952510176,
            "e_long_tail": -0.696969696969697
        },
        {
            "active_devs": 1.0,
            "num_commits": -0.9944441975198898,
            "num_files": -0.9901549386701097,
            "num_emails": 0.9249576373759381,
            "c_percentage": -0.28,
            "e_percentage": 0.28772635814889336,
            "inactive_c": -0.6799999999999999,
            "inactive_e": -1.0,
            "c_nodes": -0.5909090909090908,
            "c_edges": -0.8648648648648649,
            "c_c_coef": 0.7322751322751322,
            "c_mean_degree": -0.5693367786391043,
            "c_long_tail": -0.5714285714285714,
            "e_nodes": 1.0,
            "e_edges": 1.0,
            "e_c_coef": -0.4710115255157288,
            "e_mean_degree": 0.9441824335571214,
            "e_long_tail": 1.0
        }
    ]
}