{
    "project_id": "project_37",
    "status": "1",
    "history": [
        {
            "active_devs": -0.9182156133828996,
            "num_commits": -1.0,
            "num_files": -1.0,
            "num_emails": -0.9813883299798792,
            "c_percentage": -1.0,
            "e_percentage": 0.18918918918918926,
            "inactive_c": 1.0,
            "inactive_e": -0.33333333333333337,
            "c_nodes": -1.0,
            "c_edges": -1.0,
            "c_c_coef": -1.0,
            "c_mean_degree": -1.0,
            "c_long_tail": -1.0,
            "e_nodes": -0.9033457249070632,
            "e_edges": -0.9817351598173516,
            "e_c_coef": -1.0,
            "e_mean_degree": -0.6326061997703789,
            "e_long_tail": -0.696969696969697
        },
        {
            "active_devs": -0.7695167286245354,
            "num_commits": -0.9951383487054117,
            "num_files": -0.9783271249576702,
            "num_emails": -0.8817907444668008,
            "c_percentage": 0.9314285714285713,
            "e_percentage": 0.1914893617021276,
            "inactive_c": -1.0,
            "inactive_e": -0.7241379310344829,
            "c_nodes": -1.0,
            "c_edges": -1.0,
            "c_c_coef": -1.0,
            "c_mean_degree": -1.0,
            "c_long_tail": -1.0,
            "e_nodes": -0.7323420074349443,
            "e_edges": -0.9056316590563166,
            "e_c_coef": -0.38191438191438176,
            "e_mean_degree": -0.31453841901603097,
            "e_long_tail": -0.8181818181818181
        },
        {
            "active_devs": -0.7992565055762082,
            "num_commits": -0.9931381264584954,
            "num_files": -0.963088384693532,
            "num_emails": -0.885814889336016,
            "c_percentage": 0.51417004048583,
            "e_percentage": 0.05726872246696035,
            "inactive_c": -0.39130434782608703,
            "inactive_e": -0.76,
            "c_nodes": -0.8421052631578947,
            "c_edges": -0.9844961240310077,
            "c_c_coef": -1.0,
            "c_mean_degree": -0.8708010335917313,
            "c_long_tail": -0.92,
            "e_nodes": -0.7769516728624535,
            "e_edges": -0.9208523592085236,
            "e_c_coef": -0.7598168498168498,
            "e_mean_degree": -0.31011608623548925,
            "e_long_tail": -0.5757575757575757
        },
        {
            "active_devs": -0.79182156133829,
            "num_commits": -0.9958884320480054,
            "num_files": -0.9678293261090416,
            "num_emails": -0.8656941649899397,
            "c_percentage": 0.3783783783783783,
            "e_percentage": 0.13857677902621712,
            "inactive_c": -0.3571428571428572,
            "inactive_e": -0.6551724137931034,
            "c_nodes": -0.8421052631578947,
            "c_edges": -0.9767441860465116,
            "c_c_coef": 1.0,
            "c_mean_degree": -0.8062015503875969,
            "c_long_tail": -1.0,
            "e_nodes": -0.79182156133829,
            "e_edges": -0.93455098934551,
            "e_c_coef": -0.7023809523809523,
            "e_mean_degree": -0.38877043354655283,
            "e_long_tail": -0.09090909090909083
        }
    ]
}